sigmoid_piecewise_approx/rtl/mult.v
//////////////////////////////////////////////////////////////////////////////////
// Engineer    : casp-er
// Design Name : Multiplier Fixed Point
// Module Name : mult
// Project Name: Variational Autoencoder
//////////////////////////////////////////////////////////////////////////////////

module mult (
    
   input [15:0] Operand_1, 
   input [15:0] Operand_2,
   output [15:0] result
);

wire [31:0] temp_op1, temp_op2;
wire [63:0]temp;

assign temp_op1 = {{16{Operand_1[15]}}, Operand_1}; 
assign temp_op2 = {{16{Operand_2[15]}}, Operand_2};

assign temp = temp_op1 * temp_op2;
assign result[15:0] = temp[24:8];
endmodule

sigmoid_piecewise_approx/rtl/gradient_offset.v

module gradient_offset (
    
   input [15:0] input_grad,
   output reg [15:0] out_grad,
   output reg [15:0] out_offset

);

wire [3:0] select;
wire [3:0] pre_overflow;
wire overflow;

wire [10:0] not_in;
wire [10:0] temp_2s;

// Handling overflow
assign pre_overflow = {4{input_grad[15]}} ^ input_grad[14:11]; // Sign handling
assign overflow = pre_overflow[3] | pre_overflow[2] | pre_overflow[1] | pre_overflow[0];

// assign overflow = input_grad[15]^(input_grad[14]|input_grad[13]|input_grad[12]|input_grad[11]); //handling overflow

assign not_in = input_grad[15]? ~input_grad[10:0]:input_grad[10:0]; //handling 
assign temp_2s = not_in + input_grad[15];

assign select[3] = overflow;
assign select[2:0] = temp_2s[10:8];

always @(*) begin //gradient 
case (select)
    4'b0000  : out_grad = 16'h003B;
    4'b0001  : out_grad = 16'h0026;
    4'b0010  : out_grad = 16'h0012;
    4'b0011  : out_grad = 16'h0008;
    4'b0100  : out_grad = 16'h0003;
    4'b0101  : out_grad = 16'h0001;    
    default : out_grad = 16'h0000;

endcase
end

//offset handling
reg [15:0] temp_offset_2;
reg [15:0] temp_offset;


always @(*) begin //offset
case (select)
    4'b0000  : temp_offset = 16'h0080;
    4'b0001  : temp_offset = 16'h0090;
    4'b0010  : temp_offset = 16'h00BD;
    4'b0011  : temp_offset = 16'h00DD;
    4'b0100  : temp_offset = 16'h00F0;
    4'b0101  : temp_offset = 16'h00F9;    
    default : temp_offset = 16'h0100;

endcase

temp_offset_2 = input_grad[15]? ~temp_offset:temp_offset; //handling 
out_offset =  temp_offset_2 + {{7'b0000000,input_grad[15]},{7'b0000000,input_grad[15]}}; 

end

endmodule

sigmoid_piecewise_approx/rtl/sigmoid.v
//////////////////////////////////////////////////////////////////////////////////
// Engineer    : casp-er
// Design Name : PLA Sigmoid
// Module Name : sigmoid
// Project Name: Variational Autoencoder
//////////////////////////////////////////////////////////////////////////////////


module sigmoid #(
	parameter BITS = 16
)(
	input [BITS-1:0] x,
	output  [BITS-1:0] alfa
);
	// Initialize wire
	wire [BITS-1:0] mult_result;	
	wire [BITS-1:0] gradient;	
	wire [BITS-1:0] offset;

	wire [BITS-1:0] not_in;	
	wire [BITS-1:0] abs;	


assign not_in = x[15]? ~x[BITS-1:0]:x[BITS-1:0]; //absolute operation 
assign abs = not_in + x[15]; //absolute operation

    gradient_offset gradient_0 (
        .input_grad(x),
        .out_grad(gradient),
        .out_offset(offset)

    );
	
	// Multiplier
	mult mult_inst (
	.Operand_1(x), .Operand_2(gradient),
	.result(mult_result)
	);
	
	// Calculate alfa
    assign alfa = mult_result + offset; // Update alfa based on the combinational logic
endmodule

sigmoid_piecewise_approx/rtl/tb_sigmoid.v
`timescale 1ns / 1ps

module tb_sigmoid_2;
    // Parameters
    parameter BITS = 16;

    // Inputs
    reg [BITS-1:0] x;
    wire [BITS-1:0] gradient;
    wire [BITS-1:0] offset;

    // Output
    wire [BITS-1:0] alfa;

    // Instantiate the Unit Under Test (UUT)
    sigmoid #(.BITS(BITS)) uut (
        .x(x),
        .alfa(alfa)
    );



    // Stimulus process
    initial begin
        // Initialize inputs
        x = 0;

        // Test case 1: 
        x = 16'h0000;     // 0
      //  gradient = 16'h003B; // 0.23106
       // offset = 16'h0080; // 0.5
        #10; // Wait for 10 time units
        $display("Test Case 1 - x: %h, gradient: %h, offset: %h, alfa: %h", x, gradient, offset, alfa);

        // Test case 2: 
        x = 16'h0100;     // 1
       // gradient = 16'h0026; // 0.14794
       // offset = 16'h0090; // 0.56125
        #10;
        $display("Test Case 2 - x: %h, gradient: %h, offset: %h, alfa: %h", x, gradient, offset, alfa);

        // Test case 3: 
        x = 16'h0200;     // 2
      //  gradient = 16'h0012; // 0.07177
      //  offset = 16'h00BD; // 0.73725
        #10;
        $display("Test Case 3 - x: %h, gradient: %h, offset: %h, alfa: %h", x, gradient, offset, alfa);

        // Test case 4: 
        x = 16'h0300;     // 3
      //  gradient = 16'h0008; // 0.029439
      //  offset = 16'h00DD; // 0.864253
        #10;
        $display("Test Case 4 - x: %h, gradient: %h, offset: %h, alfa: %h", x, gradient, offset, alfa);

        // Test case 5: 
        x = 16'h0400;     // 4
      //  gradient = 16'h0003; // 0.011293
       // offset = 16'h00F0; // 0.936841
        #10;
        $display("Test Case 5 - x: %h, gradient: %h, offset: %h, alfa: %h", x, gradient, offset, alfa);
		
		// Test case 6: 
        x = 16'h0500;     // 5
      //  gradient = 16'h0001; // 0.00422
      //  offset = 16'h00F9; // 0.973307
        #10;
        $display("Test Case 6 - x: %h, gradient: %h, offset: %h, alfa: %h", x, gradient, offset, alfa);
        
		// Test case 7: 
        x = 16'hFF00;     // -1
     //   gradient = 16'h0026; // 0.14794
      //  offset = 16'h0090; // 0.56125
        #10;
        $display("Test Case 7 - x: %h, gradient: %h, offset: %h, alfa: %h", x, gradient, offset, alfa);
		
		// Test case 8: 
        x = 16'hFE00;     // -2
      //  gradient = 16'h0012; // 0.07177
     //   offset = 16'h00BD; // 0.73725
        #10;
        $display("Test Case 8 - x: %h, gradient: %h, offset: %h, alfa: %h", x, gradient, offset, alfa);
		
		// Test case 9: 
        x = 16'hFD00;     // -3
      //  gradient = 16'h0008; // 0.029439
     //   offset = 16'h00DD; // 0.864253
        #10;
        $display("Test Case 9 - x: %h, gradient: %h, offset: %h, alfa: %h", x, gradient, offset, alfa);
		
		// Test case 10: 
        x = 16'hFC00;     // -4
      //  gradient = 16'h0003; // 0.011293
      //  offset = 16'h00F0; // 0.936841
        #10;
        $display("Test Case 10 - x: %h, gradient: %h, offset: %h, alfa: %h", x, gradient, offset, alfa);
		
		// Test case 11: 
        x = 16'hFB00;     // -5
      //  gradient = 16'h0001; // 0.00422
      //  offset = 16'h00F9; // 0.973307
        #10;
        $display("Test Case 11 - x: %h, gradient: %h, offset: %h, alfa: %h", x, gradient, offset, alfa);
		
			
		// Finish simulation
        $finish;
    end

    // Optional: Waveform dump for ModelSim/QuestaSim
    initial begin
        $dumpfile("sigmoid_tb_2.vcd");
        $dumpvars(0, tb_sigmoid_2);
    end
endmodule

sigmoid_piecewise_approx/rtl/sigmoid_tb_2.vcd
$date
	Sat Nov 23 17:35:59 2024
$end
$version
	Icarus Verilog
$end
$timescale
	1ps
$end
$scope module tb_sigmoid_2 $end
$var wire 16 ! gradient [15:0] $end
$var wire 16 " offset [15:0] $end
$var wire 16 # alfa [15:0] $end
$var parameter 32 $ BITS $end
$var reg 16 % x [15:0] $end
$scope module uut $end
$var wire 16 & x [15:0] $end
$var wire 16 ' offset [15:0] $end
$var wire 16 ( not_in [15:0] $end
$var wire 16 ) mult_result [15:0] $end
$var wire 16 * gradient [15:0] $end
$var wire 16 + alfa [15:0] $end
$var wire 16 , abs [15:0] $end
$var parameter 32 - BITS $end
$scope module gradient_0 $end
$var wire 16 . input_grad [15:0] $end
$var wire 1 / overflow $end
$var wire 4 0 pre_overflow [3:0] $end
$var wire 11 1 temp_2s [10:0] $end
$var wire 4 2 select [3:0] $end
$var wire 11 3 not_in [10:0] $end
$var reg 16 4 out_grad [15:0] $end
$var reg 16 5 out_offset [15:0] $end
$var reg 16 6 temp_offset [15:0] $end
$var reg 16 7 temp_offset_2 [15:0] $end
$upscope $end
$scope module mult_inst $end
$var wire 16 8 Operand_1 [15:0] $end
$var wire 16 9 Operand_2 [15:0] $end
$var wire 32 : temp_op2 [31:0] $end
$var wire 32 ; temp_op1 [31:0] $end
$var wire 64 < temp [63:0] $end
$var wire 16 = result [15:0] $end
$upscope $end
$upscope $end
$upscope $end
$enddefinitions $end
$comment Show the parameter values. $end
$dumpall
b10000 -
b10000 $
$end
#0
$dumpvars
b0 =
b0 <
b0 ;
b111011 :
b111011 9
b0 8
b10000000 7
b10000000 6
b10000000 5
b111011 4
b0 3
b0 2
b0 1
b0 0
0/
b0 .
b0 ,
b10000000 +
b111011 *
b0 )
b0 (
b10000000 '
b0 &
b0 %
b10000000 #
bz "
bz !
$end
#10000
b10010000 '
b10010000 5
b10010000 7
b10010000 6
b100110 :
b100110 *
b100110 4
b100110 9
b1 2
b100000000 1
b100000000 3
b10110110 #
b10110110 +
b100110 )
b100110 =
b100000000 ,
b100000000 (
b10011000000000 <
b100000000 ;
b100000000 %
b100000000 &
b100000000 .
b100000000 8
#20000
b10111101 '
b10111101 5
b10111101 7
b10111101 6
b10010 :
b10010 *
b10010 4
b10010 9
b10 2
b1000000000 1
b1000000000 3
b11100001 #
b11100001 +
b100100 )
b100100 =
b1000000000 ,
b1000000000 (
b10010000000000 <
b1000000000 ;
b1000000000 %
b1000000000 &
b1000000000 .
b1000000000 8
#30000
b11011101 '
b11011101 5
b11011101 7
b11011101 6
b1000 :
b1000 *
b1000 4
b1000 9
b11 2
b1100000000 1
b1100000000 3
b11110101 #
b11110101 +
b11000 )
b11000 =
b1100000000 ,
b1100000000 (
b1100000000000 <
b1100000000 ;
b1100000000 %
b1100000000 &
b1100000000 .
b1100000000 8
#40000
b11110000 '
b11110000 5
b11110000 7
b11110000 6
b11 :
b11 *
b11 4
b11 9
b100 2
b10000000000 1
b10000000000 3
b11111100 #
b11111100 +
b1100 )
b1100 =
b10000000000 ,
b10000000000 (
b110000000000 <
b10000000000 ;
b10000000000 %
b10000000000 &
b10000000000 .
b10000000000 8
#50000
b11111001 '
b11111001 5
b11111001 7
b11111001 6
b1 :
b1 *
b1 4
b1 9
b101 2
b10100000000 1
b10100000000 3
b11111110 #
b11111110 +
b101 )
b101 =
b10100000000 ,
b10100000000 (
b10100000000 <
b10100000000 ;
b10100000000 %
b10100000000 &
b10100000000 .
b10100000000 8
#60000
b10010000 6
b100110 :
b100110 *
b100110 4
b100110 9
b1 2
b11111111 3
b1111111111011010 )
b1111111111011010 =
b11111111 (
b100000000 ,
b1001010 #
b1001010 +
b1110000 '
b1110000 5
b1111111101101111 7
b100000000 1
b10010111111111111111111101101000000000 <
b11111111111111111111111100000000 ;
b1111111100000000 %
b1111111100000000 &
b1111111100000000 .
b1111111100000000 8
#70000
b1000011 '
b1000011 5
b1111111101000010 7
b10111101 6
b10010 :
b10010 *
b10010 4
b10010 9
b10 2
b1000000000 1
b111111111 3
b1000000000 ,
b111111111 (
b11111 #
b11111 +
b1111111111011100 )
b1111111111011100 =
b1000111111111111111111101110000000000 <
b11111111111111111111111000000000 ;
b1111111000000000 %
b1111111000000000 &
b1111111000000000 .
b1111111000000000 8
#80000
b100011 '
b100011 5
b1111111100100010 7
b11011101 6
b1000 :
b1000 *
b1000 4
b1000 9
b11 2
b1100000000 1
b1011111111 3
b1100000000 ,
b1011111111 (
b1011 #
b1011 +
b1111111111101000 )
b1111111111101000 =
b11111111111111111111110100000000000 <
b11111111111111111111110100000000 ;
b1111110100000000 %
b1111110100000000 &
b1111110100000000 .
b1111110100000000 8
#90000
b10000 '
b10000 5
b1111111100001111 7
b11110000 6
b11 :
b11 *
b11 4
b11 9
b100 2
b10000000000 1
b1111111111 3
b10000000000 ,
b1111111111 (
b100 #
b100 +
b1111111111110100 )
b1111111111110100 =
b1011111111111111111111010000000000 <
b11111111111111111111110000000000 ;
b1111110000000000 %
b1111110000000000 &
b1111110000000000 .
b1111110000000000 8
#100000
b111 '
b111 5
b1111111100000110 7
b11111001 6
b1 :
b1 *
b1 4
b1 9
b101 2
b10100000000 1
b10011111111 3
b10100000000 ,
b10011111111 (
b10 #
b10 +
b1111111111111011 )
b1111111111111011 =
b11111111111111111111101100000000 <
b11111111111111111111101100000000 ;
b1111101100000000 %
b1111101100000000 &
b1111101100000000 .
b1111101100000000 8
