rtl/mult.v
//////////////////////////////////////////////////////////////////////////////////
// Engineer    : casp-er
// Design Name : Multiplier Fixed Point
// Module Name : mult
// Project Name: Variational Autoencoder
//////////////////////////////////////////////////////////////////////////////////

module mult #(
    parameter WIDTH = 16,
    parameter FRAC_WIDTH = 8
)(
    
   input [WIDTH-1:0] Operand_1, 
   input [WIDTH-1:0] Operand_2,
   output [WIDTH-1:0] result
);

wire [2*WIDTH-1:0] temp_op1, temp_op2;
wire [4*WIDTH-1:0]temp;

assign temp_op1 = {{WIDTH{Operand_1[WIDTH-1]}}, Operand_1}; 
assign temp_op2 = {{WIDTH{Operand_2[WIDTH-1]}}, Operand_2};

assign temp = temp_op1 * temp_op2;
assign result[WIDTH-1:0] = temp[WIDTH+FRAC_WIDTH:FRAC_WIDTH];
endmodule

sigmoid_piecewise_approx/rtl/gradient_offset.v

module gradient_offset (
    
   input [15:0] input_grad,
   output reg [15:0] out_grad,
   output reg [15:0] out_offset

);

wire [3:0] select;
wire [3:0] pre_overflow;
wire overflow;

wire [10:0] not_in;
wire [10:0] temp_2s;

// Handling overflow
assign pre_overflow = {4{input_grad[15]}} ^ input_grad[14:11]; // Sign handling
assign overflow = pre_overflow[3] | pre_overflow[2] | pre_overflow[1] | pre_overflow[0];

// assign overflow = input_grad[15]^(input_grad[14]|input_grad[13]|input_grad[12]|input_grad[11]); //handling overflow

assign not_in = input_grad[15]? ~input_grad[10:0]:input_grad[10:0]; //handling 
assign temp_2s = not_in + input_grad[15];

assign select[3] = overflow;
assign select[2:0] = temp_2s[10:8];

always @(*) begin //gradient 
case (select)
    4'b0000  : out_grad = 16'h003B;
    4'b0001  : out_grad = 16'h0026;
    4'b0010  : out_grad = 16'h0012;
    4'b0011  : out_grad = 16'h0008;
    4'b0100  : out_grad = 16'h0003;
    4'b0101  : out_grad = 16'h0001;    
    default : out_grad = 16'h0000;

endcase
end

//offset handling
reg [15:0] temp_offset_2;
reg [15:0] temp_offset;


always @(*) begin //offset
case (select)
    4'b0000  : temp_offset = 16'h0080;
    4'b0001  : temp_offset = 16'h0093;
    4'b0010  : temp_offset = 16'h00BD;
    4'b0011  : temp_offset = 16'h00DD;
    4'b0100  : temp_offset = 16'h00F0;
    4'b0101  : temp_offset = 16'h00F9;    
    default : temp_offset = 16'h0100;

endcase

temp_offset_2 = input_grad[15]? ~temp_offset:temp_offset; //handling 
out_offset =  temp_offset_2 + {{7'b0000000,input_grad[15]},{7'b0000000,input_grad[15]}}; 

end

endmodule

Top Level Forward/sigmoid.v
//////////////////////////////////////////////////////////////////////////////////
// Engineer    : casp-er
// Design Name : PLA Sigmoid
// Module Name : sigmoid
// Project Name: Variational Autoencoder
//////////////////////////////////////////////////////////////////////////////////


module sigmoid #(
	parameter BITS = 16
)(
	input [BITS-1:0] x,
	output  [BITS-1:0] alfa
);
	// Initialize wire
	wire [BITS-1:0] mult_result;	
	wire [BITS-1:0] gradient;	
	wire [BITS-1:0] offset;

	wire [BITS-1:0] not_in;	
	wire [BITS-1:0] abs;	


assign not_in = x[15]? ~x[BITS-1:0]:x[BITS-1:0]; //absolute operation 
assign abs = not_in + x[15]; //absolute operation

    gradient_offset gradient_0 (
        .input_grad(x),
        .out_grad(gradient),
        .out_offset(offset)

    );
	
	// Multiplier
	mult mult_inst (
	.Operand_1(x), .Operand_2(gradient),
	.result(mult_result)
	);
	
	// Calculate alfa
    assign alfa = mult_result + offset; // Update alfa based on the combinational logic
endmodule

sigmoid_piecewise_approx/testbench/sigmoid_tb.v
`timescale 1ns/1ps

module sigmoid_tb ();

    /****************************************************************************
    * Parameter
    ***************************************************************************/
	parameter WIDTH = 16;
	integer fd;	// For opening files
	integer i;

   /****************************************************************************
    * Signals
    ***************************************************************************/

   // reg clock, rst;

   reg signed [WIDTH-1:0] x;
   wire signed[WIDTH-1:0] alfa;

   /****************************************************************************
    * Generate Clock Signals
    ***************************************************************************/

	// 250 MHz clock
   // initial clock = 1'b1;
   // always #2 clock = ~clock;

   /****************************************************************************
    * Instantiate Modules
    ***************************************************************************/

	sigmoid #(.BITS(WIDTH)) uut (
      .x(x),
      .alfa(alfa)
    );

   /****************************************************************************
    * Apply Stimulus
    ***************************************************************************/

   initial begin
		$dumpfile("wave.vcd");
		$dumpvars(0,sigmoid_tb);

		// x = 16'h0000;
		// fd = $fopen("softplus_result.txt","w");
		// #2 $fwriteb(fd, x); $fwriteb(fd," "); $fwriteb(fd,alfa); $fwriteb(fd," "); $fdisplayh(fd,alfa);

		// x = 16'h0100;
		// #2 $fwriteb(fd, x); $fwriteb(fd," "); $fwriteb(fd,alfa); $fwriteb(fd," "); $fdisplayh(fd,alfa);

		fd = $fopen("result_sigmoid.txt","w");
		for (i=16'hf900; i <= 16'hffff; i=i+1) begin
			x = i;
			#2 $fwriteb(fd, x); $fwriteb(fd," "); $fwriteb(fd,alfa); $fwriteb(fd," "); $fdisplayh(fd,alfa);
		end

		for (i=16'h0000; i <= 16'h0700; i=i+1) begin
			x = i;
			#2 $fwriteb(fd, x); $fwriteb(fd," "); $fwriteb(fd,alfa); $fwriteb(fd," "); $fdisplayh(fd,alfa);
		end

		#2 $fclose(fd);	
      $finish;

   end


endmodule

3by3_image/sigmoid_piecewise_approx/wave.vcd
$date
	Tue Nov 26 06:11:44 2024
$end
$version
	Icarus Verilog
$end
$timescale
	1ps
$end
$scope module sigmoid_tb $end
$var wire 16 ! alfa [15:0] $end
$var parameter 32 " WIDTH $end
$var reg 16 # x [15:0] $end
$var integer 32 $ fd [31:0] $end
$var integer 32 % i [31:0] $end
$scope module uut $end
$var wire 16 & x [15:0] $end
$var wire 16 ' offset [15:0] $end
$var wire 16 ( not_in [15:0] $end
$var wire 16 ) mult_result [15:0] $end
$var wire 16 * gradient [15:0] $end
$var wire 16 + alfa [15:0] $end
$var wire 16 , abs [15:0] $end
$var parameter 32 - BITS $end
$scope module gradient_0 $end
$var wire 16 . input_grad [15:0] $end
$var wire 1 / overflow $end
$var wire 4 0 pre_overflow [3:0] $end
$var wire 11 1 temp_2s [10:0] $end
$var wire 4 2 select [3:0] $end
$var wire 11 3 not_in [10:0] $end
$var reg 16 4 out_grad [15:0] $end
$var reg 16 5 out_offset [15:0] $end
$var reg 16 6 temp_offset [15:0] $end
$var reg 16 7 temp_offset_2 [15:0] $end
$upscope $end
$scope module mult_inst $end
$var wire 16 8 Operand_1 [15:0] $end
$var wire 16 9 Operand_2 [15:0] $end
$var wire 32 : temp_op2 [31:0] $end
$var wire 32 ; temp_op1 [31:0] $end
$var wire 64 < temp [63:0] $end
$var wire 16 = result [15:0] $end
$upscope $end
$upscope $end
$upscope $end
$enddefinitions $end
$comment Show the parameter values. $end
$dumpall
b10000 -
b10000 "
$end
#0
$dumpvars
b0 =
b0 <
b11111111111111111111100100000000 ;
b0 :
b0 9
b1111100100000000 8
b1111111011111111 7
b100000000 6
b0 5
b0 4
b11011111111 3
b111 2
b11100000000 1
b0 0
0/
b1111100100000000 .
b11100000000 ,
b0 +
b0 *
b0 )
b11011111111 (
b0 '
b1111100100000000 &
b1111100100000000 %
b10000000000000000000000000000011 $
b1111100100000000 #
b0 !
$end
#2000
b110 2
b11011111111 1
b11011111110 3
b11011111111 ,
b11011111110 (
b11111111111111111111100100000001 ;
b1111100100000001 #
b1111100100000001 &
b1111100100000001 .
b1111100100000001 8
b1111100100000001 %
#4000
b11011111110 1
b11011111101 3
b11011111110 ,
b11011111101 (
b11111111111111111111100100000010 ;
b1111100100000010 #
b1111100100000010 &
b1111100100000010 .
b1111100100000010 8
b1111100100000010 %
#6000
b11011111101 1
b11011111100 3
b11011111101 ,
b11011111100 (
b11111111111111111111100100000011 ;
b1111100100000011 #
b1111100100000011 &
b1111100100000011 .
b1111100100000011 8
b1111100100000011 %
#8000
b11011111100 1
b11011111011 3
b11011111100 ,
b11011111011 (
b11111111111111111111100100000100 ;
b1111100100000100 #
b1111100100000100 &
b1111100100000100 .
b1111100100000100 8
b1111100100000100 %
#10000
b11011111011 1
b11011111010 3
b11011111011 ,
b11011111010 (
b11111111111111111111100100000101 ;
b1111100100000101 #
b1111100100000101 &
b1111100100000101 .
b1111100100000101 8
b1111100100000101 %
#12000
b11011111010 1
b11011111001 3
b11011111010 ,
b11011111001 (
b11111111111111111111100100000110 ;
b1111100100000110 #
b1111100100000110 &
b1111100100000110 .
b1111100100000110 8
b1111100100000110 %
#14000
b11011111001 1
b11011111000 3
b11011111001 ,
b11011111000 (
b11111111111111111111100100000111 ;
b1111100100000111 #
b1111100100000111 &
b1111100100000111 .
b1111100100000111 8
b1111100100000111 %
#16000
b11011111000 1
b11011110111 3
b11011111000 ,
b11011110111 (
b11111111111111111111100100001000 ;
b1111100100001000 #
b1111100100001000 &
b1111100100001000 .
b1111100100001000 8
b1111100100001000 %
#18000
b11011110111 1
b11011110110 3
b11011110111 ,
b11011110110 (
b11111111111111111111100100001001 ;
b1111100100001001 #
b1111100100001001 &
b1111100100001001 .
b1111100100001001 8
b1111100100001001 %
#20000
b11011110110 1
b11011110101 3
b11011110110 ,
b11011110101 (
b11111111111111111111100100001010 ;
b1111100100001010 #
b1111100100001010 &
b1111100100001010 .
b1111100100001010 8
b1111100100001010 %
#22000
b11011110101 1
b11011110100 3
b11011110101 ,
b11011110100 (
b11111111111111111111100100001011 ;
b1111100100001011 #
b1111100100001011 &
b1111100100001011 .
b1111100100001011 8
b1111100100001011 %
#24000
b11011110100 1
b11011110011 3
b11011110100 ,
b11011110011 (
b11111111111111111111100100001100 ;
b1111100100001100 #
b1111100100001100 &
b1111100100001100 .
b1111100100001100 8
b1111100100001100 %
#26000
b11011110011 1
b11011110010 3
b11011110011 ,
b11011110010 (
b11111111111111111111100100001101 ;
b1111100100001101 #
b1111100100001101 &
b1111100100001101 .
b1111100100001101 8
b1111100100001101 %
#28000
b11011110010 1
b11011110001 3
b11011110010 ,
b11011110001 (
b11111111111111111111100100001110 ;
b1111100100001110 #
b1111100100001110 &
b1111100100001110 .
b1111100100001110 8
b1111100100001110 %
#30000
b11011110001 1
b11011110000 3
b11011110001 ,
b11011110000 (
b11111111111111111111100100001111 ;
b1111100100001111 #
b1111100100001111 &
b1111100100001111 .
b1111100100001111 8
b1111100100001111 %
#32000
b11011110000 1
b11011101111 3
b11011110000 ,
b11011101111 (
b11111111111111111111100100010000 ;
b1111100100010000 #
b1111100100010000 &
b1111100100010000 .
b1111100100010000 8
b1111100100010000 %
#34000
b11011101111 1
b11011101110 3
b11011101111 ,
b11011101110 (
b11111111111111111111100100010001 ;
b1111100100010001 #
b1111100100010001 &
b1111100100010001 .
b1111100100010001 8
b1111100100010001 %
#36000
b11011101110 1
b11011101101 3
b11011101110 ,
b11011101101 (
b11111111111111111111100100010010 ;
b1111100100010010 #
b1111100100010010 &
b1111100100010010 .
b1111100100010010 8
b1111100100010010 %
#38000
b11011101101 1
b11011101100 3
b11011101101 ,
b11011101100 (
b11111111111111111111100100010011 ;
b1111100100010011 #
b1111100100010011 &
b1111100100010011 .
b1111100100010011 8
b1111100100010011 %
#40000
b11011101100 1
b11011101011 3
b11011101100 ,
b11011101011 (
b11111111111111111111100100010100 ;
b1111100100010100 #
b1111100100010100 &
b1111100100010100 .
b1111100100010100 8
b1111100100010100 %
#42000
b11011101011 1
b11011101010 3
b11011101011 ,
b11011101010 (
b11111111111111111111100100010101 ;
b1111100100010101 #
b1111100100010101 &
b1111100100010101 .
b1111100100010101 8
b1111100100010101 %
#44000
b11011101010 1
b11011101001 3
b11011101010 ,
b11011101001 (
b11111111111111111111100100010110 ;
b1111100100010110 #
b1111100100010110 &
b1111100100010110 .
b1111100100010110 8
b1111100100010110 %
#46000
b11011101001 1
b11011101000 3
b11011101001 ,
b11011101000 (
b11111111111111111111100100010111 ;
b1111100100010111 #
b1111100100010111 &
b1111100100010111 .
b1111100100010111 8
b1111100100010111 %
#48000
b11011101000 1
b11011100111 3
b11011101000 ,
b11011100111 (
b11111111111111111111100100011000 ;
b1111100100011000 #
b1111100100011000 &
b1111100100011000 .
b1111100100011000 8
b1111100100011000 %
#50000
b11011100111 1
b11011100110 3
b11011100111 ,
b11011100110 (
b11111111111111111111100100011001 ;
b1111100100011001 #
b1111100100011001 &
b1111100100011001 .
b1111100100011001 8
b1111100100011001 %
#52000
b11011100110 1
b11011100101 3
b11011100110 ,
b11011100101 (
b11111111111111111111100100011010 ;
b1111100100011010 #
b1111100100011010 &
b1111100100011010 .
b1111100100011010 8
b1111100100011010 %
#54000
b11011100101 1
b11011100100 3
b11011100101 ,
b11011100100 (
b11111111111111111111100100011011 ;
b1111100100011011 #
b1111100100011011 &
b1111100100011011 .
b1111100100011011 8
b1111100100011011 %
#56000
b11011100100 1
b11011100011 3
b11011100100 ,
b11011100011 (
b11111111111111111111100100011100 ;
b1111100100011100 #
b1111100100011100 &
b1111100100011100 .
b1111100100011100 8
b1111100100011100 %
#58000
b11011100011 1
b11011100010 3
b11011100011 ,
b11011100010 (
b11111111111111111111100100011101 ;
b1111100100011101 #
b1111100100011101 &
b1111100100011101 .
b1111100100011101 8
b1111100100011101 %
#60000
b11011100010 1
b11011100001 3
b11011100010 ,
b11011100001 (
b11111111111111111111100100011110 ;
b1111100100011110 #
b1111100100011110 &
b1111100100011110 .
b1111100100011110 8
b1111100100011110 %
#62000
b11011100001 1
b11011100000 3
b11011100001 ,
b11011100000 (
b11111111111111111111100100011111 ;
b1111100100011111 #
b1111100100011111 &
b1111100100011111 .
b1111100100011111 8
b1111100100011111 %
#64000
b11011100000 1
b11011011111 3
b11011100000 ,
b11011011111 (
b11111111111111111111100100100000 ;
b1111100100100000 #
b1111100100100000 &
b1111100100100000 .
b1111100100100000 8
b1111100100100000 %
#66000
b11011011111 1
b11011011110 3
b11011011111 ,
b11011011110 (
b11111111111111111111100100100001 ;
b1111100100100001 #
b1111100100100001 &
b1111100100100001 .
b1111100100100001 8
b1111100100100001 %
#68000
b11011011110 1
b11011011101 3
b11011011110 ,
b11011011101 (
b11111111111111111111100100100010 ;
b1111100100100010 #
b1111100100100010 &
b1111100100100010 .
b1111100100100010 8
b1111100100100010 %
#70000
b11011011101 1
b11011011100 3
b11011011101 ,
b11011011100 (
b11111111111111111111100100100011 ;
b1111100100100011 #
b1111100100100011 &
b1111100100100011 .
b1111100100100011 8
b1111100100100011 %
#72000
b11011011100 1
b11011011011 3
b11011011100 ,
b11011011011 (
b11111111111111111111100100100100 ;
b1111100100100100 #
b1111100100100100 &
b1111100100100100 .
b1111100100100100 8
b1111100100100100 %
#74000
b11011011011 1
b11011011010 3
b11011011011 ,
b11011011010 (
b11111111111111111111100100100101 ;
b1111100100100101 #
b1111100100100101 &
b1111100100100101 .
b1111100100100101 8
b1111100100100101 %
#76000
b11011011010 1
b11011011001 3
b11011011010 ,
b11011011001 (
b11111111111111111111100100100110 ;
b1111100100100110 #
b1111100100100110 &
b1111100100100110 .
b1111100100100110 8
b1111100100100110 %
#78000
b11011011001 1
b11011011000 3
b11011011001 ,
b11011011000 (
b11111111111111111111100100100111 ;
b1111100100100111 #
b1111100100100111 &
b1111100100100111 .
b1111100100100111 8
b1111100100100111 %
#80000
b11011011000 1
b11011010111 3
b11011011000 ,
b11011010111 (
b11111111111111111111100100101000 ;
b1111100100101000 #
b1111100100101000 &
b1111100100101000 .
b1111100100101000 8
b1111100100101000 %
#82000
b11011010111 1
b11011010110 3
b11011010111 ,
b11011010110 (
b11111111111111111111100100101001 ;
b1111100100101001 #
b1111100100101001 &
b1111100100101001 .
b1111100100101001 8
b1111100100101001 %
#84000
b11011010110 1
b11011010101 3
b11011010110 ,
b11011010101 (
b11111111111111111111100100101010 ;
b1111100100101010 #
b1111100100101010 &
b1111100100101010 .
b1111100100101010 8
b1111100100101010 %
#86000
b11011010101 1
b11011010100 3
b11011010101 ,
b11011010100 (
b11111111111111111111100100101011 ;
b1111100100101011 #
b1111100100101011 &
b1111100100101011 .
b1111100100101011 8
b1111100100101011 %
#88000
b11011010100 1
b11011010011 3
b11011010100 ,
b11011010011 (
b11111111111111111111100100101100 ;
b1111100100101100 #
b1111100100101100 &
b1111100100101100 .
b1111100100101100 8
b1111100100101100 %
#90000
b11011010011 1
b11011010010 3
b11011010011 ,
b11011010010 (
b11111111111111111111100100101101 ;
b1111100100101101 #
b1111100100101101 &
b1111100100101101 .
b1111100100101101 8
b1111100100101101 %
#92000
b11011010010 1
b11011010001 3
b11011010010 ,
b11011010001 (
b11111111111111111111100100101110 ;
b1111100100101110 #
b1111100100101110 &
b1111100100101110 .
b1111100100101110 8
b1111100100101110 %
#94000
b11011010001 1
b11011010000 3
b11011010001 ,
b11011010000 (
b11111111111111111111100100101111 ;
b1111100100101111 #
b1111100100101111 &
b1111100100101111 .
b1111100100101111 8
b1111100100101111 %
#96000
b11011010000 1
b11011001111 3
b11011010000 ,
b11011001111 (
b11111111111111111111100100110000 ;
b1111100100110000 #
b1111100100110000 &
b1111100100110000 .
b1111100100110000 8
b1111100100110000 %
#98000
b11011001111 1
b11011001110 3
b11011001111 ,
b11011001110 (
b11111111111111111111100100110001 ;
b1111100100110001 #
b1111100100110001 &
b1111100100110001 .
b1111100100110001 8
b1111100100110001 %
#100000
b11011001110 1
b11011001101 3
b11011001110 ,
b11011001101 (
b11111111111111111111100100110010 ;
b1111100100110010 #
b1111100100110010 &
b1111100100110010 .
b1111100100110010 8
b1111100100110010 %
#102000
b11011001101 1
b11011001100 3
b11011001101 ,
b11011001100 (
b11111111111111111111100100110011 ;
b1111100100110011 #
b1111100100110011 &
b1111100100110011 .
b1111100100110011 8
b1111100100110011 %
#104000
b11011001100 1
b11011001011 3
b11011001100 ,
b11011001011 (
b11111111111111111111100100110100 ;
b1111100100110100 #
b1111100100110100 &
b1111100100110100 .
b1111100100110100 8
b1111100100110100 %
#106000
b11011001011 1
b11011001010 3
b11011001011 ,
b11011001010 (
b11111111111111111111100100110101 ;
b1111100100110101 #
b1111100100110101 &
b1111100100110101 .
b1111100100110101 8
b1111100100110101 %
#108000
b11011001010 1
b11011001001 3
b11011001010 ,
b11011001001 (
b11111111111111111111100100110110 ;
b1111100100110110 #
b1111100100110110 &
b1111100100110110 .
b1111100100110110 8
b1111100100110110 %
#110000
b11011001001 1
b11011001000 3
b11011001001 ,
b11011001000 (
b11111111111111111111100100110111 ;
b1111100100110111 #
b1111100100110111 &
b1111100100110111 .
b1111100100110111 8
b1111100100110111 %
#112000
b11011001000 1
b11011000111 3
b11011001000 ,
b11011000111 (
b11111111111111111111100100111000 ;
b1111100100111000 #
b1111100100111000 &
b1111100100111000 .
b1111100100111000 8
b1111100100111000 %
#114000
b11011000111 1
b11011000110 3
b11011000111 ,
b11011000110 (
b11111111111111111111100100111001 ;
b1111100100111001 #
b1111100100111001 &
b1111100100111001 .
b1111100100111001 8
b1111100100111001 %
#116000
b11011000110 1
b11011000101 3
b11011000110 ,
b11011000101 (
b11111111111111111111100100111010 ;
b1111100100111010 #
b1111100100111010 &
b1111100100111010 .
b1111100100111010 8
b1111100100111010 %
#118000
b11011000101 1
b11011000100 3
b11011000101 ,
b11011000100 (
b11111111111111111111100100111011 ;
b1111100100111011 #
b1111100100111011 &
b1111100100111011 .
b1111100100111011 8
b1111100100111011 %
#120000
b11011000100 1
b11011000011 3
b11011000100 ,
b11011000011 (
b11111111111111111111100100111100 ;
b1111100100111100 #
b1111100100111100 &
b1111100100111100 .
b1111100100111100 8
b1111100100111100 %
#122000
b11011000011 1
b11011000010 3
b11011000011 ,
b11011000010 (
b11111111111111111111100100111101 ;
b1111100100111101 #
b1111100100111101 &
b1111100100111101 .
b1111100100111101 8
b1111100100111101 %
#124000
b11011000010 1
b11011000001 3
b11011000010 ,
b11011000001 (
b11111111111111111111100100111110 ;
b1111100100111110 #
b1111100100111110 &
b1111100100111110 .
b1111100100111110 8
b1111100100111110 %
#126000
b11011000001 1
b11011000000 3
b11011000001 ,
b11011000000 (
b11111111111111111111100100111111 ;
b1111100100111111 #
b1111100100111111 &
b1111100100111111 .
b1111100100111111 8
b1111100100111111 %
#128000
b11011000000 1
b11010111111 3
b11011000000 ,
b11010111111 (
b11111111111111111111100101000000 ;
b1111100101000000 #
b1111100101000000 &
b1111100101000000 .
b1111100101000000 8
b1111100101000000 %
#130000
b11010111111 1
b11010111110 3
b11010111111 ,
b11010111110 (
b11111111111111111111100101000001 ;
b1111100101000001 #
b1111100101000001 &
b1111100101000001 .
b1111100101000001 8
b1111100101000001 %
#132000
b11010111110 1
b11010111101 3
b11010111110 ,
b11010111101 (
b11111111111111111111100101000010 ;
b1111100101000010 #
b1111100101000010 &
b1111100101000010 .
b1111100101000010 8
b1111100101000010 %
#134000
b11010111101 1
b11010111100 3
b11010111101 ,
b11010111100 (
b11111111111111111111100101000011 ;
b1111100101000011 #
b1111100101000011 &
b1111100101000011 .
b1111100101000011 8
b1111100101000011 %
#136000
b11010111100 1
b11010111011 3
b11010111100 ,
b11010111011 (
b11111111111111111111100101000100 ;
b1111100101000100 #
b1111100101000100 &
b1111100101000100 .
b1111100101000100 8
b1111100101000100 %
#138000
b11010111011 1
b11010111010 3
b11010111011 ,
b11010111010 (
b11111111111111111111100101000101 ;
b1111100101000101 #
b1111100101000101 &
b1111100101000101 .
b1111100101000101 8
b1111100101000101 %
#140000
b11010111010 1
b11010111001 3
b11010111010 ,
b11010111001 (
b11111111111111111111100101000110 ;
b1111100101000110 #
b1111100101000110 &
b1111100101000110 .
b1111100101000110 8
b1111100101000110 %
#142000
b11010111001 1
b11010111000 3
b11010111001 ,
b11010111000 (
b11111111111111111111100101000111 ;
b1111100101000111 #
b1111100101000111 &
b1111100101000111 .
b1111100101000111 8
b1111100101000111 %
#144000
b11010111000 1
b11010110111 3
b11010111000 ,
b11010110111 (
b11111111111111111111100101001000 ;
b1111100101001000 #
b1111100101001000 &
b1111100101001000 .
b1111100101001000 8
b1111100101001000 %
#146000
b11010110111 1
b11010110110 3
b11010110111 ,
b11010110110 (
b11111111111111111111100101001001 ;
b1111100101001001 #
b1111100101001001 &
b1111100101001001 .
b1111100101001001 8
b1111100101001001 %
#148000
b11010110110 1
b11010110101 3
b11010110110 ,
b11010110101 (
b11111111111111111111100101001010 ;
b1111100101001010 #
b1111100101001010 &
b1111100101001010 .
b1111100101001010 8
b1111100101001010 %
#150000
b11010110101 1
b11010110100 3
b11010110101 ,
b11010110100 (
b11111111111111111111100101001011 ;
b1111100101001011 #
b1111100101001011 &
b1111100101001011 .
b1111100101001011 8
b1111100101001011 %
#152000
b11010110100 1
b11010110011 3
b11010110100 ,
b11010110011 (
b11111111111111111111100101001100 ;
b1111100101001100 #
b1111100101001100 &
b1111100101001100 .
b1111100101001100 8
b1111100101001100 %
#154000
b11010110011 1
b11010110010 3
b11010110011 ,
b11010110010 (
b11111111111111111111100101001101 ;
b1111100101001101 #
b1111100101001101 &
b1111100101001101 .
b1111100101001101 8
b1111100101001101 %
#156000
b11010110010 1
b11010110001 3
b11010110010 ,
b11010110001 (
b11111111111111111111100101001110 ;
b1111100101001110 #
b1111100101001110 &
b1111100101001110 .
b1111100101001110 8
b1111100101001110 %
#158000
b11010110001 1
b11010110000 3
b11010110001 ,
b11010110000 (
b11111111111111111111100101001111 ;
b1111100101001111 #
b1111100101001111 &
b1111100101001111 .
b1111100101001111 8
b1111100101001111 %
#160000
b11010110000 1
b11010101111 3
b11010110000 ,
b11010101111 (
b11111111111111111111100101010000 ;
b1111100101010000 #
b1111100101010000 &
b1111100101010000 .
b1111100101010000 8
b1111100101010000 %
#162000
b11010101111 1
b11010101110 3
b11010101111 ,
b11010101110 (
b11111111111111111111100101010001 ;
b1111100101010001 #
b1111100101010001 &
b1111100101010001 .
b1111100101010001 8
b1111100101010001 %
#164000
b11010101110 1
b11010101101 3
b11010101110 ,
b11010101101 (
b11111111111111111111100101010010 ;
b1111100101010010 #
b1111100101010010 &
b1111100101010010 .
b1111100101010010 8
b1111100101010010 %
#166000
b11010101101 1
b11010101100 3
b11010101101 ,
b11010101100 (
b11111111111111111111100101010011 ;
b1111100101010011 #
b1111100101010011 &
b1111100101010011 .
b1111100101010011 8
b1111100101010011 %
#168000
b11010101100 1
b11010101011 3
b11010101100 ,
b11010101011 (
b11111111111111111111100101010100 ;
b1111100101010100 #
b1111100101010100 &
b1111100101010100 .
b1111100101010100 8
b1111100101010100 %
#170000
b11010101011 1
b11010101010 3
b11010101011 ,
b11010101010 (
b11111111111111111111100101010101 ;
b1111100101010101 #
b1111100101010101 &
b1111100101010101 .
b1111100101010101 8
b1111100101010101 %
#172000
b11010101010 1
b11010101001 3
b11010101010 ,
b11010101001 (
b11111111111111111111100101010110 ;
b1111100101010110 #
b1111100101010110 &
b1111100101010110 .
b1111100101010110 8
b1111100101010110 %
#174000
b11010101001 1
b11010101000 3
b11010101001 ,
b11010101000 (
b11111111111111111111100101010111 ;
b1111100101010111 #
b1111100101010111 &
b1111100101010111 .
b1111100101010111 8
b1111100101010111 %
#176000
b11010101000 1
b11010100111 3
b11010101000 ,
b11010100111 (
b11111111111111111111100101011000 ;
b1111100101011000 #
b1111100101011000 &
b1111100101011000 .
b1111100101011000 8
b1111100101011000 %
#178000
b11010100111 1
b11010100110 3
b11010100111 ,
b11010100110 (
b11111111111111111111100101011001 ;
b1111100101011001 #
b1111100101011001 &
b1111100101011001 .
b1111100101011001 8
b1111100101011001 %
#180000
b11010100110 1
b11010100101 3
b11010100110 ,
b11010100101 (
b11111111111111111111100101011010 ;
b1111100101011010 #
b1111100101011010 &
b1111100101011010 .
b1111100101011010 8
b1111100101011010 %
#182000
b11010100101 1
b11010100100 3
b11010100101 ,
b11010100100 (
b11111111111111111111100101011011 ;
b1111100101011011 #
b1111100101011011 &
b1111100101011011 .
b1111100101011011 8
b1111100101011011 %
#184000
b11010100100 1
b11010100011 3
b11010100100 ,
b11010100011 (
b11111111111111111111100101011100 ;
b1111100101011100 #
b1111100101011100 &
b1111100101011100 .
b1111100101011100 8
b1111100101011100 %
#186000
b11010100011 1
b11010100010 3
b11010100011 ,
b11010100010 (
b11111111111111111111100101011101 ;
b1111100101011101 #
b1111100101011101 &
b1111100101011101 .
b1111100101011101 8
b1111100101011101 %
#188000
b11010100010 1
b11010100001 3
b11010100010 ,
b11010100001 (
b11111111111111111111100101011110 ;
b1111100101011110 #
b1111100101011110 &
b1111100101011110 .
b1111100101011110 8
b1111100101011110 %
#190000
b11010100001 1
b11010100000 3
b11010100001 ,
b11010100000 (
b11111111111111111111100101011111 ;
b1111100101011111 #
b1111100101011111 &
b1111100101011111 .
b1111100101011111 8
b1111100101011111 %
#192000
b11010100000 1
b11010011111 3
b11010100000 ,
b11010011111 (
b11111111111111111111100101100000 ;
b1111100101100000 #
b1111100101100000 &
b1111100101100000 .
b1111100101100000 8
b1111100101100000 %
#194000
b11010011111 1
b11010011110 3
b11010011111 ,
b11010011110 (
b11111111111111111111100101100001 ;
b1111100101100001 #
b1111100101100001 &
b1111100101100001 .
b1111100101100001 8
b1111100101100001 %
#196000
b11010011110 1
b11010011101 3
b11010011110 ,
b11010011101 (
b11111111111111111111100101100010 ;
b1111100101100010 #
b1111100101100010 &
b1111100101100010 .
b1111100101100010 8
b1111100101100010 %
#198000
b11010011101 1
b11010011100 3
b11010011101 ,
b11010011100 (
b11111111111111111111100101100011 ;
b1111100101100011 #
b1111100101100011 &
b1111100101100011 .
b1111100101100011 8
b1111100101100011 %
#200000
b11010011100 1
b11010011011 3
b11010011100 ,
b11010011011 (
b11111111111111111111100101100100 ;
b1111100101100100 #
b1111100101100100 &
b1111100101100100 .
b1111100101100100 8
b1111100101100100 %
#202000
b11010011011 1
b11010011010 3
b11010011011 ,
b11010011010 (
b11111111111111111111100101100101 ;
b1111100101100101 #
b1111100101100101 &
b1111100101100101 .
b1111100101100101 8
b1111100101100101 %
#204000
b11010011010 1
b11010011001 3
b11010011010 ,
b11010011001 (
b11111111111111111111100101100110 ;
b1111100101100110 #
b1111100101100110 &
b1111100101100110 .
b1111100101100110 8
b1111100101100110 %
#206000
b11010011001 1
b11010011000 3
b11010011001 ,
b11010011000 (
b11111111111111111111100101100111 ;
b1111100101100111 #
b1111100101100111 &
b1111100101100111 .
b1111100101100111 8
b1111100101100111 %
#208000
b11010011000 1
b11010010111 3
b11010011000 ,
b11010010111 (
b11111111111111111111100101101000 ;
b1111100101101000 #
b1111100101101000 &
b1111100101101000 .
b1111100101101000 8
b1111100101101000 %
#210000
b11010010111 1
b11010010110 3
b11010010111 ,
b11010010110 (
b11111111111111111111100101101001 ;
b1111100101101001 #
b1111100101101001 &
b1111100101101001 .
b1111100101101001 8
b1111100101101001 %
#212000
b11010010110 1
b11010010101 3
b11010010110 ,
b11010010101 (
b11111111111111111111100101101010 ;
b1111100101101010 #
b1111100101101010 &
b1111100101101010 .
b1111100101101010 8
b1111100101101010 %
#214000
b11010010101 1
b11010010100 3
b11010010101 ,
b11010010100 (
b11111111111111111111100101101011 ;
b1111100101101011 #
b1111100101101011 &
b1111100101101011 .
b1111100101101011 8
b1111100101101011 %
#216000
b11010010100 1
b11010010011 3
b11010010100 ,
b11010010011 (
b11111111111111111111100101101100 ;
b1111100101101100 #
b1111100101101100 &
b1111100101101100 .
b1111100101101100 8
b1111100101101100 %
#218000
b11010010011 1
b11010010010 3
b11010010011 ,
b11010010010 (
b11111111111111111111100101101101 ;
b1111100101101101 #
b1111100101101101 &
b1111100101101101 .
b1111100101101101 8
b1111100101101101 %
#220000
b11010010010 1
b11010010001 3
b11010010010 ,
b11010010001 (
b11111111111111111111100101101110 ;
b1111100101101110 #
b1111100101101110 &
b1111100101101110 .
b1111100101101110 8
b1111100101101110 %
