rtl/mult.v
//////////////////////////////////////////////////////////////////////////////////
// Engineer    : casp-er
// Design Name : Multiplier Fixed Point
// Module Name : mult
// Project Name: Variational Autoencoder
//////////////////////////////////////////////////////////////////////////////////

module mult #(
    parameter WIDTH = 16,
    parameter FRAC_WIDTH = 8
)(
    
   input [WIDTH-1:0] Operand_1, 
   input [WIDTH-1:0] Operand_2,
   output [WIDTH-1:0] result
);

wire [2*WIDTH-1:0] temp_op1, temp_op2;
wire [4*WIDTH-1:0]temp;

assign temp_op1 = {{WIDTH{Operand_1[WIDTH-1]}}, Operand_1}; 
assign temp_op2 = {{WIDTH{Operand_2[WIDTH-1]}}, Operand_2};

assign temp = temp_op1 * temp_op2;
assign result[WIDTH-1:0] = temp[WIDTH+FRAC_WIDTH:FRAC_WIDTH];
endmodule

softplus_piecewise_approx/rtl/off_softplus.v
//////////////////////////////////////////////////////////////////////////////////
// Engineer    : casp-er
// Design Name : Offset SoftPlus
// Module Name : off_softplus
// Project Name: Variational Autoencoder
//////////////////////////////////////////////////////////////////////////////////

module off_softplus (
   input [15:0] operand, 
   output reg [15:0] offset
);

	wire [7:0] x;
	wire sign;
	reg [15:0] outpos;
	reg [15:0] outneg;
	assign sign = operand[15];
	assign x = operand[15:8];

	always @ (*) begin
		case(x)
		  8'h00   	: outpos = 16'h004d; 		// 0
		  8'h01  	: outpos = 16'h0037; 		// 1
		  8'h02   	: outpos = 16'h001f; 		// 2
		  8'h03   	: outpos = 16'h000f; 		// 3
		  8'h04   	: outpos = 16'h0007; 		// 4
		  default  	: outpos = 16'h004d; 		// Default
		endcase
		
		case(x)
		  8'hff   	: outneg = 16'h004d; 		// -1
		  8'hfe   	: outneg = 16'h0037; 		// -2
		  8'hfd   	: outneg = 16'h001f; 		// -3
		  8'hfc   	: outneg = 16'h000f; 		// -4
		  8'hfb   	: outneg = 16'h0007; 		// -5
		  default  	: outneg = 16'h0002; 		// Default
		endcase
		
		case(sign)
		  0   		: offset = outpos; 		// Positve
		  default   : offset = outneg; 		// Default
		endcase
	end
endmodule

softplus_piecewise_approx/rtl/grad_softplus.v
//////////////////////////////////////////////////////////////////////////////////
// Engineer    : casp-er
// Design Name : Gradien SoftPlus
// Module Name : grad_softplus
// Project Name: Variational Autoencoder
//////////////////////////////////////////////////////////////////////////////////

module grad_softplus (
    
   input [15:0] operand, 
   output reg [15:0] grad
);

	wire [7:0] x;
	wire sign;
	reg [15:0] outpos;
	reg [15:0] outneg;
	assign sign = operand[15];
	assign x = operand[15:8];

	always @ (*) begin
		case(x)
		  8'h00   	: outpos = 16'h0044; 		// 0
		  8'h01   	: outpos = 16'h005a; 		// 1
		  8'h02   	: outpos = 16'h0066; 		// 2
		  8'h03   	: outpos = 16'h006b; 		// 3
		  8'h04   	: outpos = 16'h006d; 		// 4
		  default  	: outpos = 16'h006e; 		// Default
		endcase
		
		case(x)
		  8'hfb   	: outneg = 16'h0001; 		// -1
		  8'hfc   	: outneg = 16'h0003; 		// -2
		  8'hfd   	: outneg = 16'h0008; 		// -3
		  8'hfe   	: outneg = 16'h0014; 		// -4
		  8'hff   	: outneg = 16'h002a; 		// -5
		  default  	: outneg = 16'h0000; 		// Default
		endcase
		
		case(sign)
		  0   		: grad = outpos; 		// Positve
		  default   : grad = outneg; 		// Default
		endcase
	end
endmodule

softplus_piecewise_approx/rtl/softplus.v
//////////////////////////////////////////////////////////////////////////////////
// Engineer    : casp-er
// Design Name : SoftPlus
// Module Name : softplus
// Project Name: Variational Autoencoder
//////////////////////////////////////////////////////////////////////////////////

// `include "mult.v"
// `include "grad_softplus.v"
// `include "off_softplus.v"
module softplus (
   input [15:0] operand, 
   output [15:0] out
);
	wire [15:0] grad;
	wire [15:0] offset;
	wire [15:0] mulres;
	
	grad_softplus softgrad
		(
			.operand(operand),
			.grad(grad)
		);
		
	off_softplus softoff
		(
			.operand(operand),
			.offset(offset)
		);
	
	mult softmul
		(
			.Operand_1(operand),
			.Operand_2(grad),
			.result(mulres)
		);
	
	assign out = mulres + offset;
endmodule

softplus_piecewise_approx/rtl/tb_softplus.v
`timescale 1ns / 1ps
`include "softplus.v"


module tb_softplus;

    // Inputs
    reg [15:0] x;
    wire [15:0] gradient;
    wire [15:0] offset;

    // Output
    wire [15:0] alfa;

    // Instantiate the Unit Under Test (UUT)
    softplus #() uut (
        .operand(x),
        .out(alfa)
    );



    // Stimulus process
    initial begin
        // Initialize inputs
        x = 0;

        // Test case 1: 
        x = 16'h0000;     // 0
      //  gradient = 16'h003B; // 0.23106
       // offset = 16'h0080; // 0.5
        #10; // Wait for 10 time units
        $display("Test Case 1 - x: %h, gradient: %h, offset: %h, alfa: %h", x, gradient, offset, alfa);

        // Test case 2: 
        x = 16'h0100;     // 1
       // gradient = 16'h0026; // 0.14794
       // offset = 16'h0090; // 0.56125
        #10;
        $display("Test Case 2 - x: %h, gradient: %h, offset: %h, alfa: %h", x, gradient, offset, alfa);

        // Test case 3: 
        x = 16'h0200;     // 2
      //  gradient = 16'h0012; // 0.07177
      //  offset = 16'h00BD; // 0.73725
        #10;
        $display("Test Case 3 - x: %h, gradient: %h, offset: %h, alfa: %h", x, gradient, offset, alfa);

        // Test case 4: 
        x = 16'h0300;     // 3
      //  gradient = 16'h0008; // 0.029439
      //  offset = 16'h00DD; // 0.864253
        #10;
        $display("Test Case 4 - x: %h, gradient: %h, offset: %h, alfa: %h", x, gradient, offset, alfa);

        // Test case 5: 
        x = 16'h0400;     // 4
      //  gradient = 16'h0003; // 0.011293
       // offset = 16'h00F0; // 0.936841
        #10;
        $display("Test Case 5 - x: %h, gradient: %h, offset: %h, alfa: %h", x, gradient, offset, alfa);
		
		// Test case 6: 
        x = 16'h0500;     // 5
      //  gradient = 16'h0001; // 0.00422
      //  offset = 16'h00F9; // 0.973307
        #10;
        $display("Test Case 6 - x: %h, gradient: %h, offset: %h, alfa: %h", x, gradient, offset, alfa);
        
		// Test case 7: 
        x = 16'hFF00;     // -1
     //   gradient = 16'h0026; // 0.14794
      //  offset = 16'h0090; // 0.56125
        #10;
        $display("Test Case 7 - x: %h, gradient: %h, offset: %h, alfa: %h", x, gradient, offset, alfa);
		
		// Test case 8: 
        x = 16'hFE00;     // -2
      //  gradient = 16'h0012; // 0.07177
     //   offset = 16'h00BD; // 0.73725
        #10;
        $display("Test Case 8 - x: %h, gradient: %h, offset: %h, alfa: %h", x, gradient, offset, alfa);
		
		// Test case 9: 
        x = 16'hFD00;     // -3
      //  gradient = 16'h0008; // 0.029439
     //   offset = 16'h00DD; // 0.864253
        #10;
        $display("Test Case 9 - x: %h, gradient: %h, offset: %h, alfa: %h", x, gradient, offset, alfa);
		
		// Test case 10: 
        x = 16'hFC00;     // -4
      //  gradient = 16'h0003; // 0.011293
      //  offset = 16'h00F0; // 0.936841
        #10;
        $display("Test Case 10 - x: %h, gradient: %h, offset: %h, alfa: %h", x, gradient, offset, alfa);
		
		// Test case 11: 
        x = 16'hFB00;     // -5
      //  gradient = 16'h0001; // 0.00422
      //  offset = 16'h00F9; // 0.973307
        #10;
        $display("Test Case 11 - x: %h, gradient: %h, offset: %h, alfa: %h", x, gradient, offset, alfa);
		
			
		// Finish simulation
        $finish;
    end

    // Optional: Waveform dump for ModelSim/QuestaSim
    initial begin
        $dumpfile("softplus_tb.vcd");
        $dumpvars(0, tb_softplus);
    end
endmodule

softplus_piecewise_approx/rtl/softplus_tb.vcd
$date
	Sat Nov 23 20:02:18 2024
$end
$version
	Icarus Verilog
$end
$timescale
	1ps
$end
$scope module tb_softplus $end
$var wire 16 ! gradient [15:0] $end
$var wire 16 " offset [15:0] $end
$var wire 16 # alfa [15:0] $end
$var reg 16 $ x [15:0] $end
$scope module uut $end
$var wire 16 % operand [15:0] $end
$var wire 16 & out [15:0] $end
$var wire 16 ' offset [15:0] $end
$var wire 16 ( mulres [15:0] $end
$var wire 16 ) grad [15:0] $end
$scope module softgrad $end
$var wire 16 * operand [15:0] $end
$var wire 8 + x [7:0] $end
$var wire 1 , sign $end
$var reg 16 - grad [15:0] $end
$var reg 16 . outneg [15:0] $end
$var reg 16 / outpos [15:0] $end
$upscope $end
$scope module softmul $end
$var wire 16 0 Operand_1 [15:0] $end
$var wire 16 1 Operand_2 [15:0] $end
$var wire 32 2 temp_op2 [31:0] $end
$var wire 32 3 temp_op1 [31:0] $end
$var wire 64 4 temp [63:0] $end
$var wire 16 5 result [15:0] $end
$upscope $end
$scope module softoff $end
$var wire 16 6 operand [15:0] $end
$var wire 8 7 x [7:0] $end
$var wire 1 8 sign $end
$var reg 16 9 offset [15:0] $end
$var reg 16 : outneg [15:0] $end
$var reg 16 ; outpos [15:0] $end
$upscope $end
$upscope $end
$upscope $end
$enddefinitions $end
$comment Show the parameter values. $end
$dumpall
$end
#0
$dumpvars
b1001101 ;
b10 :
b1001101 9
08
b0 7
b0 6
b0 5
b0 4
b0 3
b1000100 2
b1000100 1
b0 0
b1000100 /
b0 .
b1000100 -
0,
b0 +
b0 *
b1000100 )
b0 (
b1001101 '
b1001101 &
b0 %
b0 $
b1001101 #
bz "
bz !
$end
#10000
b1011010 2
b1011010 )
b1011010 -
b1011010 1
b1011010 /
b1011010 (
b1011010 5
b10010001 #
b10010001 &
b110111 '
b110111 9
b110111 ;
b1 +
b1 7
b101101000000000 4
b100000000 3
b100000000 $
b100000000 %
b100000000 *
b100000000 0
b100000000 6
#20000
b1100110 2
b1100110 )
b1100110 -
b1100110 1
b1100110 /
b11001100 (
b11001100 5
b11101011 #
b11101011 &
b11111 '
b11111 9
b11111 ;
b10 +
b10 7
b1100110000000000 4
b1000000000 3
b1000000000 $
b1000000000 %
b1000000000 *
b1000000000 0
b1000000000 6
#30000
b1101011 2
b1101011 )
b1101011 -
b1101011 1
b1101011 /
b101000001 (
b101000001 5
b101010000 #
b101010000 &
b1111 '
b1111 9
b1111 ;
b11 +
b11 7
b10100000100000000 4
b1100000000 3
b1100000000 $
b1100000000 %
b1100000000 *
b1100000000 0
b1100000000 6
#40000
b1101101 2
b1101101 )
b1101101 -
b1101101 1
b1101101 /
b110110100 (
b110110100 5
b110111011 #
b110111011 &
b111 '
b111 9
b111 ;
b100 +
b100 7
b11011010000000000 4
b10000000000 3
b10000000000 $
b10000000000 %
b10000000000 *
b10000000000 0
b10000000000 6
#50000
b1101110 2
b1101110 )
b1101110 -
b1101110 1
b1101110 /
b1000100110 (
b1000100110 5
b1001110011 #
b1001110011 &
b1001101 '
b1001101 9
b1001101 ;
b101 +
b101 7
b100010011000000000 4
b10100000000 3
b10100000000 $
b10100000000 %
b10100000000 *
b10100000000 0
b10100000000 6
#60000
b101010 2
b101010 )
b101010 -
b101010 1
b101010 .
b100011 #
b100011 &
b1111111111010110 (
b1111111111010110 5
b1001101 :
1,
b11111111 +
18
b11111111 7
b10100111111111111111111101011000000000 4
b11111111111111111111111100000000 3
b1111111100000000 $
b1111111100000000 %
b1111111100000000 *
b1111111100000000 0
b1111111100000000 6
#70000
b10100 2
b10100 )
b10100 -
b10100 1
b10100 .
b1111111111011000 (
b1111111111011000 5
b1111 #
b1111 &
b110111 '
b110111 9
b110111 :
b11111110 +
b11111110 7
b1001111111111111111111101100000000000 4
b11111111111111111111111000000000 3
b1111111000000000 $
b1111111000000000 %
b1111111000000000 *
b1111111000000000 0
b1111111000000000 6
#80000
b1000 2
b1000 )
b1000 -
b1000 1
b1000 .
b1111111111101000 (
b1111111111101000 5
b111 #
b111 &
b11111 '
b11111 9
b11111 :
b11111101 +
b11111101 7
b11111111111111111111110100000000000 4
b11111111111111111111110100000000 3
b1111110100000000 $
b1111110100000000 %
b1111110100000000 *
b1111110100000000 0
b1111110100000000 6
#90000
b11 2
b11 )
b11 -
b11 1
b11 .
b1111111111110100 (
b1111111111110100 5
b11 #
b11 &
b1111 '
b1111 9
b1111 :
b11111100 +
b11111100 7
b1011111111111111111111010000000000 4
b11111111111111111111110000000000 3
b1111110000000000 $
b1111110000000000 %
b1111110000000000 *
b1111110000000000 0
b1111110000000000 6
#100000
b1 2
b1 )
b1 -
b1 1
b1 .
b1111111111111011 (
b1111111111111011 5
b10 #
b10 &
b111 '
b111 9
b111 :
b11111011 +
b11111011 7
b11111111111111111111101100000000 4
b11111111111111111111101100000000 3
b1111101100000000 $
b1111101100000000 %
b1111101100000000 *
b1111101100000000 0
b1111101100000000 6
