rtl/XORShift_RNG.v
// this is a module for random number generator based on XORShift algorithm

module XOR_RNG (
    input wire clk,          // Clock input
    input wire rst,          // Reset input (synchronous)
    output reg [7:0] rand    // 8-bit random output
);

    // Internal state register
    reg [7:0] state;

    always @(posedge clk) begin
        if (rst) begin
            // Initialize with a non-zero seed
            state = 8'h4D;  // Example seed value (must be non-zero)
        end else begin
            // Xorshift operations
        //    state <= update_state;
            state <= state ^ (state << 3);  // Shift left by 3 and XOR
            state <= state ^ (state >> 5);  // Shift right by 5 and XOR
            state <= state ^ (state << 2);  // Shift left by 2 and XOR
            state <= state  + 8'h11; // Add a constant for feedback

        end
    end

    // Assign the state to the random output
    always @(posedge clk) begin
        rand <= state;

    end

endmodule

XORShift_RNG/XOR_RNG_tb.v
module testbench;
    reg clk;
    reg rst;
    wire [7:0] rand;

    // Instantiate the xorshift RNG module
    XOR_RNG random_0 (
        .clk(clk),
        .rst(rst),
        .rand(rand)
    );

    // Clock generation
    initial begin
        clk = 0;
        forever #5 clk = ~clk;  // 10ns clock period
    end

    // Test sequence
    initial begin
        rst = 1;
        #10 rst = 0;  // Release reset after 10ns
        #800 $stop;   // Stop simulation after 100ns
    end

    // Monitor output
    initial begin
        $monitor("Time: %t | Random: %h", $time, rand);
    end


        // Optional: Waveform dump for ModelSim/QuestaSim
    initial begin
        $dumpfile("testbench.vcd");
        $dumpvars(0, testbench);
    end


endmodule

3by3_image/XORShift_RNG/testbench.vcd
$date
	Sun Dec 01 20:32:21 2024
$end
$version
	Icarus Verilog
$end
$timescale
	1s
$end
$scope module testbench $end
$var wire 8 ! rand [7:0] $end
$var reg 1 " clk $end
$var reg 1 # rst $end
$scope module random_0 $end
$var wire 1 " clk $end
$var wire 1 # rst $end
$var reg 8 $ rand [7:0] $end
$var reg 8 % state [7:0] $end
$upscope $end
$upscope $end
$enddefinitions $end
$comment Show the parameter values. $end
$dumpall
$end
#0
$dumpvars
bx %
bx $
1#
0"
bx !
$end
#5
b1001101 %
1"
#10
0"
0#
#15
b1001101 !
b1001101 $
b1011110 %
1"
#20
0"
#25
b1101111 %
b1011110 !
b1011110 $
1"
#30
0"
#35
b1101111 !
b1101111 $
b10000000 %
1"
#40
0"
#45
b10010001 %
b10000000 !
b10000000 $
1"
#50
0"
#55
b10010001 !
b10010001 $
b10100010 %
1"
#60
0"
#65
b10110011 %
b10100010 !
b10100010 $
1"
#70
0"
#75
b10110011 !
b10110011 $
b11000100 %
1"
#80
0"
#85
b11010101 %
b11000100 !
b11000100 $
1"
#90
0"
#95
b11010101 !
b11010101 $
b11100110 %
1"
#100
0"
#105
b11110111 %
b11100110 !
b11100110 $
1"
#110
0"
#115
b11110111 !
b11110111 $
b1000 %
1"
#120
0"
#125
b11001 %
b1000 !
b1000 $
1"
#130
0"
#135
b11001 !
b11001 $
b101010 %
1"
#140
0"
#145
b111011 %
b101010 !
b101010 $
1"
#150
0"
#155
b111011 !
b111011 $
b1001100 %
1"
#160
0"
#165
b1011101 %
b1001100 !
b1001100 $
1"
#170
0"
#175
b1011101 !
b1011101 $
b1101110 %
1"
#180
0"
#185
b1111111 %
b1101110 !
b1101110 $
1"
#190
0"
#195
b1111111 !
b1111111 $
b10010000 %
1"
#200
0"
#205
b10100001 %
b10010000 !
b10010000 $
1"
#210
0"
#215
b10100001 !
b10100001 $
b10110010 %
1"
#220
0"
#225
b11000011 %
b10110010 !
b10110010 $
1"
#230
0"
#235
b11000011 !
b11000011 $
b11010100 %
1"
#240
0"
#245
b11100101 %
b11010100 !
b11010100 $
1"
#250
0"
#255
b11100101 !
b11100101 $
b11110110 %
1"
#260
0"
#265
b111 %
b11110110 !
b11110110 $
1"
#270
0"
#275
b111 !
b111 $
b11000 %
1"
#280
0"
#285
b101001 %
b11000 !
b11000 $
1"
#290
0"
#295
b101001 !
b101001 $
b111010 %
1"
#300
0"
#305
b1001011 %
b111010 !
b111010 $
1"
#310
0"
#315
b1001011 !
b1001011 $
b1011100 %
1"
#320
0"
#325
b1101101 %
b1011100 !
b1011100 $
1"
#330
0"
#335
b1101101 !
b1101101 $
b1111110 %
1"
#340
0"
#345
b10001111 %
b1111110 !
b1111110 $
1"
#350
0"
#355
b10001111 !
b10001111 $
b10100000 %
1"
#360
0"
#365
b10110001 %
b10100000 !
b10100000 $
1"
#370
0"
#375
b10110001 !
b10110001 $
b11000010 %
1"
#380
0"
#385
b11010011 %
b11000010 !
b11000010 $
1"
#390
0"
#395
b11010011 !
b11010011 $
b11100100 %
1"
#400
0"
#405
b11110101 %
b11100100 !
b11100100 $
1"
#410
0"
#415
b11110101 !
b11110101 $
b110 %
1"
#420
0"
#425
b10111 %
b110 !
b110 $
1"
#430
0"
#435
b10111 !
b10111 $
b101000 %
1"
#440
0"
#445
b111001 %
b101000 !
b101000 $
1"
#450
0"
#455
b111001 !
b111001 $
b1001010 %
1"
#460
0"
#465
b1011011 %
b1001010 !
b1001010 $
1"
#470
0"
#475
b1011011 !
b1011011 $
b1101100 %
1"
#480
0"
#485
b1111101 %
b1101100 !
b1101100 $
1"
#490
0"
#495
b1111101 !
b1111101 $
b10001110 %
1"
#500
0"
#505
b10011111 %
b10001110 !
b10001110 $
1"
#510
0"
#515
b10011111 !
b10011111 $
b10110000 %
1"
#520
0"
#525
b11000001 %
b10110000 !
b10110000 $
1"
#530
0"
#535
b11000001 !
b11000001 $
b11010010 %
1"
#540
0"
#545
b11100011 %
b11010010 !
b11010010 $
1"
#550
0"
#555
b11100011 !
b11100011 $
b11110100 %
1"
#560
0"
#565
b101 %
b11110100 !
b11110100 $
1"
#570
0"
#575
b101 !
b101 $
b10110 %
1"
#580
0"
#585
b100111 %
b10110 !
b10110 $
1"
#590
0"
#595
b100111 !
b100111 $
b111000 %
1"
#600
0"
#605
b1001001 %
b111000 !
b111000 $
1"
#610
0"
#615
b1001001 !
b1001001 $
b1011010 %
1"
#620
0"
#625
b1101011 %
b1011010 !
b1011010 $
1"
#630
0"
#635
b1101011 !
b1101011 $
b1111100 %
1"
#640
0"
#645
b10001101 %
b1111100 !
b1111100 $
1"
#650
0"
#655
b10001101 !
b10001101 $
b10011110 %
1"
#660
0"
#665
b10101111 %
b10011110 !
b10011110 $
1"
#670
0"
#675
b10101111 !
b10101111 $
b11000000 %
1"
#680
0"
#685
b11010001 %
b11000000 !
b11000000 $
1"
#690
0"
#695
b11010001 !
b11010001 $
b11100010 %
1"
#700
0"
#705
b11110011 %
b11100010 !
b11100010 $
1"
#710
0"
#715
b11110011 !
b11110011 $
b100 %
1"
#720
0"
#725
b10101 %
b100 !
b100 $
1"
#730
0"
#735
b10101 !
b10101 $
b100110 %
1"
#740
0"
#745
b110111 %
b100110 !
b100110 $
1"
#750
0"
#755
b110111 !
b110111 $
b1001000 %
1"
#760
0"
#765
b1011001 %
b1001000 !
b1001000 $
1"
#770
0"
#775
b1011001 !
b1011001 $
b1101010 %
1"
#780
0"
#785
b1111011 %
b1101010 !
b1101010 $
1"
#790
0"
#795
b1111011 !
b1111011 $
b10001100 %
1"
#800
0"
#805
b10011101 %
b10001100 !
b10001100 $
1"
