softplus_piecewise_approx/rtl/off_softplus.v
//////////////////////////////////////////////////////////////////////////////////
// Engineer    : casp-er
// Design Name : Offset SoftPlus
// Module Name : off_softplus
// Project Name: Variational Autoencoder
//////////////////////////////////////////////////////////////////////////////////

module off_softplus (
   input [15:0] operand, 
   output reg [15:0] offset
);

	wire [7:0] x;
	wire sign;
	reg [15:0] outpos;
	reg [15:0] outneg;
	assign sign = operand[15];
	assign x = operand[15:8];

	always @ (*) begin
		case(x)
		  8'h00   	: outpos = 16'h004d; 		// 0
		  8'h01  	: outpos = 16'h0037; 		// 1
		  8'h02   	: outpos = 16'h001f; 		// 2
		  8'h03   	: outpos = 16'h000f; 		// 3
		  8'h04   	: outpos = 16'h0007; 		// 4
		  default  	: outpos = 16'h004d; 		// Default
		endcase
		
		case(x)
		  8'hff   	: outneg = 16'h004d; 		// -1
		  8'hfe   	: outneg = 16'h0037; 		// -2
		  8'hfd   	: outneg = 16'h001f; 		// -3
		  8'hfc   	: outneg = 16'h000f; 		// -4
		  8'hfb   	: outneg = 16'h0007; 		// -5
		  default  	: outneg = 16'h0002; 		// Default
		endcase
		
		case(sign)
		  0   		: offset = outpos; 		// Positve
		  default   : offset = outneg; 		// Default
		endcase
	end
endmodule

softplus_piecewise_approx/rtl/grad_softplus.v
//////////////////////////////////////////////////////////////////////////////////
// Engineer    : casp-er
// Design Name : Gradien SoftPlus
// Module Name : grad_softplus
// Project Name: Variational Autoencoder
//////////////////////////////////////////////////////////////////////////////////

module grad_softplus (
    
   input [15:0] operand, 
   output reg [15:0] grad
);

	wire [2:0] x;
	wire sign;
	reg [15:0] outpos;
	reg [15:0] outneg;
	assign sign = operand[15];
	assign x = operand[10:8];

	always @ (*) begin
		case(x)
		  3'b000   	: outpos = 16'h0044; 		// 0
		  3'b001   	: outpos = 16'h005a; 		// 1
		  3'b010   	: outpos = 16'h0066; 		// 2
		  3'b011   	: outpos = 16'h006b; 		// 3
		  3'b100   	: outpos = 16'h006d; 		// 4
		  default  	: outpos = 16'h006e; 		// Default
		endcase
		
		case(x)
		  3'b111   	: outneg = 16'h0001; 		// -1
		  3'b110   	: outneg = 16'h0003; 		// -2
		  3'b101   	: outneg = 16'h0008; 		// -3
		  3'b100   	: outneg = 16'h0014; 		// -4
		  3'b011   	: outneg = 16'h002a; 		// -5
		  default  	: outneg = 16'h0000; 		// Default
		endcase
		
		case(sign)
		  0   		: grad = outpos; 		// Positve
		  default   : grad = outneg; 		// Default
		endcase
	end
endmodule

rtl/mult.v
//////////////////////////////////////////////////////////////////////////////////
// Engineer    : casp-er
// Design Name : Multiplier Fixed Point
// Module Name : mult
// Project Name: Variational Autoencoder
//////////////////////////////////////////////////////////////////////////////////

module mult #(
    parameter WIDTH = 16,
    parameter FRAC_WIDTH = 8
)(
    
   input [WIDTH-1:0] Operand_1, 
   input [WIDTH-1:0] Operand_2,
   output [WIDTH-1:0] result
);

wire [2*WIDTH-1:0] temp_op1, temp_op2;
wire [4*WIDTH-1:0]temp;

assign temp_op1 = {{WIDTH{Operand_1[WIDTH-1]}}, Operand_1}; 
assign temp_op2 = {{WIDTH{Operand_2[WIDTH-1]}}, Operand_2};

assign temp = temp_op1 * temp_op2;
assign result[WIDTH-1:0] = temp[WIDTH+FRAC_WIDTH:FRAC_WIDTH];
endmodule

softplus_squared_piecewise_approx/rtl/off_softplus_squared.v
//////////////////////////////////////////////////////////////////////////////////
// Engineer    : casp-er
// Design Name : Offset SoftPlus
// Module Name : off_softplus
// Project Name: Variational Autoencoder
//////////////////////////////////////////////////////////////////////////////////

module off_softplus_squared (
   input [15:0] operand, 
   output reg [15:0] offset
);

	wire [7:0] x;
	wire sign;
	reg [15:0] outpos;
	reg [15:0] outneg;
	assign sign = operand[15];
	assign x = operand[15:8];

	always @ (*) begin
		case(x)
		  8'h00   	: outpos = 16'h004d; 		// 0
		  8'h01  	: outpos = 16'h0037; 		// 1
		  8'h02   	: outpos = 16'h0020; 		// 2
		  8'h03   	: outpos = 16'h0014; 		// 3
		  8'h04   	: outpos = 16'h000b; 		// 4
		  default  	: outpos = 16'h0009; 		// Default
		endcase
		
		case(x)
		  8'hff   	: outneg = 16'h004c; 		// -1
		  8'hfe   	: outneg = 16'h0037; 		// -2
		  8'hfd   	: outneg = 16'h001f; 		// -3
		  8'hfc   	: outneg = 16'h000f; 		// -4
		  8'hfb   	: outneg = 16'h0007; 		// -5
		  default  	: outneg = 16'h0002; 		// Default
		endcase
		
		case(sign)
		  0   		: offset = outpos; 		// Positve
		  default   : offset = outneg; 		// Default
		endcase
	end
endmodule

softplus_squared_piecewise_approx/rtl/grad_softplus_squared.v
//////////////////////////////////////////////////////////////////////////////////
// Engineer    : casp-er
// Design Name : Gradien SoftPlus
// Module Name : grad_softplus
// Project Name: Variational Autoencoder
//////////////////////////////////////////////////////////////////////////////////

module grad_softplus_squared (
    
   input [15:0] operand, 
   output reg [15:0] grad
);

	wire [7:0] x;
	wire sign;
	reg [15:0] outpos;
	reg [15:0] outneg;
	assign sign = operand[15];
	assign x = operand[15:8];

	always @ (*) begin
		case(x)
		  8'h00   	: outpos = 16'h0044; 		// 0
		  8'h01   	: outpos = 16'h005a; 		// 1
		  8'h02   	: outpos = 16'h0066; 		// 2
		  8'h03   	: outpos = 16'h006b; 		// 3
		  8'h04   	: outpos = 16'h006d; 		// 4
		  default  	: outpos = 16'h006e; 		// Default
		endcase
		
		case(x)
		  8'hfb   	: outneg = 16'h0001; 		// -1
		  8'hfc   	: outneg = 16'h0003; 		// -2
		  8'hfd   	: outneg = 16'h0008; 		// -3
		  8'hfe   	: outneg = 16'h0014; 		// -4
		  8'hff   	: outneg = 16'h002a; 		// -5
		  default  	: outneg = 16'h0000; 		// Default
		endcase
		
		case(sign)
		  0   		: grad = outpos; 		// Positve
		  default   : grad = outneg; 		// Default
		endcase
	end
endmodule

Top Level Forward/rtl/softplus_squared.v
//////////////////////////////////////////////////////////////////////////////////
// Engineer    : casp-er
// Design Name : SoftPlus
// Module Name : softplus
// Project Name: Variational Autoencoder
//////////////////////////////////////////////////////////////////////////////////

// `include "mult.v"
// `include "grad_softplus.v"
// `include "off_softplus.v"
module softplus_squared (
   input [15:0] operand, 
   output [15:0] out
);
	wire [15:0] grad;
	wire [15:0] offset;
	wire [15:0] mulres;
	
	grad_softplus_squared softgrad
		(
			.operand(operand),
			.grad(grad)
		);
		
	off_softplus_squared softoff
		(
			.operand(operand),
			.offset(offset)
		);
	
	mult softmul
		(
			.Operand_1(operand),
			.Operand_2(grad),
			.result(mulres)
		);
	
	assign out = mulres + offset;
endmodule

softplus_squared_piecewise_approx/testbench/softplus_squared_tb.v
`timescale 1ns/1ps

module softplus_squared_tb ();

    /****************************************************************************
    * Parameter
    ***************************************************************************/
	parameter WIDTH = 16;
	integer fd;	// For opening files
	integer i;

   /****************************************************************************
    * Signals
    ***************************************************************************/

   // reg clock, rst;

   reg signed [WIDTH-1:0] x;
   wire signed[WIDTH-1:0] alfa;

   /****************************************************************************
    * Generate Clock Signals
    ***************************************************************************/

	// 250 MHz clock
   // initial clock = 1'b1;
   // always #2 clock = ~clock;

   /****************************************************************************
    * Instantiate Modules
    ***************************************************************************/

	softplus_squared #() uut (
		.operand(x),
		.out(alfa)
	);

   /****************************************************************************
    * Apply Stimulus
    ***************************************************************************/

   initial begin
		$dumpfile("wave.vcd");
		$dumpvars(0,softplus_squared_tb);

		// x = 16'h0000;
		// fd = $fopen("softplus_result.txt","w");
		// #2 $fwriteb(fd, x); $fwriteb(fd," "); $fwriteb(fd,alfa); $fwriteb(fd," "); $fdisplayh(fd,alfa);

		// x = 16'h0100;
		// #2 $fwriteb(fd, x); $fwriteb(fd," "); $fwriteb(fd,alfa); $fwriteb(fd," "); $fdisplayh(fd,alfa);

		fd = $fopen("result_softplus_squared.txt","w");
		for (i=16'hf800; i <= 16'hffff; i=i+1) begin
			x = i;
			#2 $fwriteb(fd, x); $fwriteb(fd," "); $fwriteb(fd,alfa); $fwriteb(fd," "); $fdisplayh(fd,alfa);
		end

		for (i=16'h0000; i <= 16'h0800; i=i+1) begin
			x = i;
			#2 $fwriteb(fd, x); $fwriteb(fd," "); $fwriteb(fd,alfa); $fwriteb(fd," "); $fdisplayh(fd,alfa);
		end

		#2 $fclose(fd);	
      $finish;

   end


endmodule

softplus_squared_piecewise_approx/wave.vcd
$date
	Sat Dec 07 21:15:52 2024
$end
$version
	Icarus Verilog
$end
$timescale
	1ps
$end
$scope module softplus_squared_tb $end
$var wire 16 ! alfa [15:0] $end
$var parameter 32 " WIDTH $end
$var reg 16 # x [15:0] $end
$var integer 32 $ fd [31:0] $end
$var integer 32 % i [31:0] $end
$scope module uut $end
$var wire 16 & operand [15:0] $end
$var wire 16 ' out [15:0] $end
$var wire 16 ( offset [15:0] $end
$var wire 16 ) mulres [15:0] $end
$var wire 16 * grad [15:0] $end
$scope module softgrad $end
$var wire 16 + operand [15:0] $end
$var wire 8 , x [7:0] $end
$var wire 1 - sign $end
$var reg 16 . grad [15:0] $end
$var reg 16 / outneg [15:0] $end
$var reg 16 0 outpos [15:0] $end
$upscope $end
$scope module softmul $end
$var wire 16 1 Operand_1 [15:0] $end
$var wire 16 2 Operand_2 [15:0] $end
$var wire 32 3 temp_op2 [31:0] $end
$var wire 32 4 temp_op1 [31:0] $end
$var wire 64 5 temp [63:0] $end
$var wire 16 6 result [15:0] $end
$upscope $end
$scope module softoff $end
$var wire 16 7 operand [15:0] $end
$var wire 8 8 x [7:0] $end
$var wire 1 9 sign $end
$var reg 16 : offset [15:0] $end
$var reg 16 ; outneg [15:0] $end
$var reg 16 < outpos [15:0] $end
$upscope $end
$upscope $end
$upscope $end
$enddefinitions $end
$comment Show the parameter values. $end
$dumpall
b10000 "
$end
#0
$dumpvars
b11100111 <
b10011 ;
b10011 :
19
b11111000 8
b1111100000000000 7
b1111111111110000 6
b111111111111111111111000000000000 5
b11111111111111111111100000000000 4
b10 3
b10 2
b1111100000000000 1
b11111 0
b10 /
b10 .
1-
b11111000 ,
b1111100000000000 +
b10 *
b1111111111110000 )
b10011 (
b11 '
b1111100000000000 &
b1111100000000000 %
b10000000000000000000000000000011 $
b1111100000000000 #
b11 !
$end
#2000
b111111111111111111111000000000010 5
b11111111111111111111100000000001 4
b1111100000000001 #
b1111100000000001 &
b1111100000000001 +
b1111100000000001 1
b1111100000000001 7
b1111100000000001 %
#4000
b111111111111111111111000000000100 5
b11111111111111111111100000000010 4
b1111100000000010 #
b1111100000000010 &
b1111100000000010 +
b1111100000000010 1
b1111100000000010 7
b1111100000000010 %
#6000
b111111111111111111111000000000110 5
b11111111111111111111100000000011 4
b1111100000000011 #
b1111100000000011 &
b1111100000000011 +
b1111100000000011 1
b1111100000000011 7
b1111100000000011 %
#8000
b111111111111111111111000000001000 5
b11111111111111111111100000000100 4
b1111100000000100 #
b1111100000000100 &
b1111100000000100 +
b1111100000000100 1
b1111100000000100 7
b1111100000000100 %
#10000
b111111111111111111111000000001010 5
b11111111111111111111100000000101 4
b1111100000000101 #
b1111100000000101 &
b1111100000000101 +
b1111100000000101 1
b1111100000000101 7
b1111100000000101 %
#12000
b111111111111111111111000000001100 5
b11111111111111111111100000000110 4
b1111100000000110 #
b1111100000000110 &
b1111100000000110 +
b1111100000000110 1
b1111100000000110 7
b1111100000000110 %
#14000
b111111111111111111111000000001110 5
b11111111111111111111100000000111 4
b1111100000000111 #
b1111100000000111 &
b1111100000000111 +
b1111100000000111 1
b1111100000000111 7
b1111100000000111 %
#16000
b111111111111111111111000000010000 5
b11111111111111111111100000001000 4
b1111100000001000 #
b1111100000001000 &
b1111100000001000 +
b1111100000001000 1
b1111100000001000 7
b1111100000001000 %
#18000
b111111111111111111111000000010010 5
b11111111111111111111100000001001 4
b1111100000001001 #
b1111100000001001 &
b1111100000001001 +
b1111100000001001 1
b1111100000001001 7
b1111100000001001 %
#20000
b111111111111111111111000000010100 5
b11111111111111111111100000001010 4
b1111100000001010 #
b1111100000001010 &
b1111100000001010 +
b1111100000001010 1
b1111100000001010 7
b1111100000001010 %
#22000
b111111111111111111111000000010110 5
b11111111111111111111100000001011 4
b1111100000001011 #
b1111100000001011 &
b1111100000001011 +
b1111100000001011 1
b1111100000001011 7
b1111100000001011 %
#24000
b111111111111111111111000000011000 5
b11111111111111111111100000001100 4
b1111100000001100 #
b1111100000001100 &
b1111100000001100 +
b1111100000001100 1
b1111100000001100 7
b1111100000001100 %
#26000
b111111111111111111111000000011010 5
b11111111111111111111100000001101 4
b1111100000001101 #
b1111100000001101 &
b1111100000001101 +
b1111100000001101 1
b1111100000001101 7
b1111100000001101 %
#28000
b111111111111111111111000000011100 5
b11111111111111111111100000001110 4
b1111100000001110 #
b1111100000001110 &
b1111100000001110 +
b1111100000001110 1
b1111100000001110 7
b1111100000001110 %
#30000
b111111111111111111111000000011110 5
b11111111111111111111100000001111 4
b1111100000001111 #
b1111100000001111 &
b1111100000001111 +
b1111100000001111 1
b1111100000001111 7
b1111100000001111 %
#32000
b111111111111111111111000000100000 5
b11111111111111111111100000010000 4
b1111100000010000 #
b1111100000010000 &
b1111100000010000 +
b1111100000010000 1
b1111100000010000 7
b1111100000010000 %
#34000
b111111111111111111111000000100010 5
b11111111111111111111100000010001 4
b1111100000010001 #
b1111100000010001 &
b1111100000010001 +
b1111100000010001 1
b1111100000010001 7
b1111100000010001 %
#36000
b111111111111111111111000000100100 5
b11111111111111111111100000010010 4
b1111100000010010 #
b1111100000010010 &
b1111100000010010 +
b1111100000010010 1
b1111100000010010 7
b1111100000010010 %
#38000
b111111111111111111111000000100110 5
b11111111111111111111100000010011 4
b1111100000010011 #
b1111100000010011 &
b1111100000010011 +
b1111100000010011 1
b1111100000010011 7
b1111100000010011 %
#40000
b111111111111111111111000000101000 5
b11111111111111111111100000010100 4
b1111100000010100 #
b1111100000010100 &
b1111100000010100 +
b1111100000010100 1
b1111100000010100 7
b1111100000010100 %
#42000
b111111111111111111111000000101010 5
b11111111111111111111100000010101 4
b1111100000010101 #
b1111100000010101 &
b1111100000010101 +
b1111100000010101 1
b1111100000010101 7
b1111100000010101 %
#44000
b111111111111111111111000000101100 5
b11111111111111111111100000010110 4
b1111100000010110 #
b1111100000010110 &
b1111100000010110 +
b1111100000010110 1
b1111100000010110 7
b1111100000010110 %
#46000
b111111111111111111111000000101110 5
b11111111111111111111100000010111 4
b1111100000010111 #
b1111100000010111 &
b1111100000010111 +
b1111100000010111 1
b1111100000010111 7
b1111100000010111 %
#48000
b111111111111111111111000000110000 5
b11111111111111111111100000011000 4
b1111100000011000 #
b1111100000011000 &
b1111100000011000 +
b1111100000011000 1
b1111100000011000 7
b1111100000011000 %
#50000
b111111111111111111111000000110010 5
b11111111111111111111100000011001 4
b1111100000011001 #
b1111100000011001 &
b1111100000011001 +
b1111100000011001 1
b1111100000011001 7
b1111100000011001 %
#52000
b111111111111111111111000000110100 5
b11111111111111111111100000011010 4
b1111100000011010 #
b1111100000011010 &
b1111100000011010 +
b1111100000011010 1
b1111100000011010 7
b1111100000011010 %
#54000
b111111111111111111111000000110110 5
b11111111111111111111100000011011 4
b1111100000011011 #
b1111100000011011 &
b1111100000011011 +
b1111100000011011 1
b1111100000011011 7
b1111100000011011 %
#56000
b111111111111111111111000000111000 5
b11111111111111111111100000011100 4
b1111100000011100 #
b1111100000011100 &
b1111100000011100 +
b1111100000011100 1
b1111100000011100 7
b1111100000011100 %
#58000
b111111111111111111111000000111010 5
b11111111111111111111100000011101 4
b1111100000011101 #
b1111100000011101 &
b1111100000011101 +
b1111100000011101 1
b1111100000011101 7
b1111100000011101 %
#60000
b111111111111111111111000000111100 5
b11111111111111111111100000011110 4
b1111100000011110 #
b1111100000011110 &
b1111100000011110 +
b1111100000011110 1
b1111100000011110 7
b1111100000011110 %
#62000
b111111111111111111111000000111110 5
b11111111111111111111100000011111 4
b1111100000011111 #
b1111100000011111 &
b1111100000011111 +
b1111100000011111 1
b1111100000011111 7
b1111100000011111 %
#64000
b111111111111111111111000001000000 5
b11111111111111111111100000100000 4
b1111100000100000 #
b1111100000100000 &
b1111100000100000 +
b1111100000100000 1
b1111100000100000 7
b1111100000100000 %
#66000
b111111111111111111111000001000010 5
b11111111111111111111100000100001 4
b1111100000100001 #
b1111100000100001 &
b1111100000100001 +
b1111100000100001 1
b1111100000100001 7
b1111100000100001 %
#68000
b111111111111111111111000001000100 5
b11111111111111111111100000100010 4
b1111100000100010 #
b1111100000100010 &
b1111100000100010 +
b1111100000100010 1
b1111100000100010 7
b1111100000100010 %
#70000
b111111111111111111111000001000110 5
b11111111111111111111100000100011 4
b1111100000100011 #
b1111100000100011 &
b1111100000100011 +
b1111100000100011 1
b1111100000100011 7
b1111100000100011 %
#72000
b111111111111111111111000001001000 5
b11111111111111111111100000100100 4
b1111100000100100 #
b1111100000100100 &
b1111100000100100 +
b1111100000100100 1
b1111100000100100 7
b1111100000100100 %
#74000
b111111111111111111111000001001010 5
b11111111111111111111100000100101 4
b1111100000100101 #
b1111100000100101 &
b1111100000100101 +
b1111100000100101 1
b1111100000100101 7
b1111100000100101 %
#76000
b111111111111111111111000001001100 5
b11111111111111111111100000100110 4
b1111100000100110 #
b1111100000100110 &
b1111100000100110 +
b1111100000100110 1
b1111100000100110 7
b1111100000100110 %
#78000
b111111111111111111111000001001110 5
b11111111111111111111100000100111 4
b1111100000100111 #
b1111100000100111 &
b1111100000100111 +
b1111100000100111 1
b1111100000100111 7
b1111100000100111 %
#80000
b111111111111111111111000001010000 5
b11111111111111111111100000101000 4
b1111100000101000 #
b1111100000101000 &
b1111100000101000 +
b1111100000101000 1
b1111100000101000 7
b1111100000101000 %
#82000
b111111111111111111111000001010010 5
b11111111111111111111100000101001 4
b1111100000101001 #
b1111100000101001 &
b1111100000101001 +
b1111100000101001 1
b1111100000101001 7
b1111100000101001 %
#84000
b111111111111111111111000001010100 5
b11111111111111111111100000101010 4
b1111100000101010 #
b1111100000101010 &
b1111100000101010 +
b1111100000101010 1
b1111100000101010 7
b1111100000101010 %
#86000
b111111111111111111111000001010110 5
b11111111111111111111100000101011 4
b1111100000101011 #
b1111100000101011 &
b1111100000101011 +
b1111100000101011 1
b1111100000101011 7
b1111100000101011 %
#88000
b111111111111111111111000001011000 5
b11111111111111111111100000101100 4
b1111100000101100 #
b1111100000101100 &
b1111100000101100 +
b1111100000101100 1
b1111100000101100 7
b1111100000101100 %
#90000
b111111111111111111111000001011010 5
b11111111111111111111100000101101 4
b1111100000101101 #
b1111100000101101 &
b1111100000101101 +
b1111100000101101 1
b1111100000101101 7
b1111100000101101 %
#92000
b111111111111111111111000001011100 5
b11111111111111111111100000101110 4
b1111100000101110 #
b1111100000101110 &
b1111100000101110 +
b1111100000101110 1
b1111100000101110 7
b1111100000101110 %
#94000
b111111111111111111111000001011110 5
b11111111111111111111100000101111 4
b1111100000101111 #
b1111100000101111 &
b1111100000101111 +
b1111100000101111 1
b1111100000101111 7
b1111100000101111 %
#96000
b111111111111111111111000001100000 5
b11111111111111111111100000110000 4
b1111100000110000 #
b1111100000110000 &
b1111100000110000 +
b1111100000110000 1
b1111100000110000 7
b1111100000110000 %
#98000
b111111111111111111111000001100010 5
b11111111111111111111100000110001 4
b1111100000110001 #
b1111100000110001 &
b1111100000110001 +
b1111100000110001 1
b1111100000110001 7
b1111100000110001 %
#100000
b111111111111111111111000001100100 5
b11111111111111111111100000110010 4
b1111100000110010 #
b1111100000110010 &
b1111100000110010 +
b1111100000110010 1
b1111100000110010 7
b1111100000110010 %
#102000
b111111111111111111111000001100110 5
b11111111111111111111100000110011 4
b1111100000110011 #
b1111100000110011 &
b1111100000110011 +
b1111100000110011 1
b1111100000110011 7
b1111100000110011 %
#104000
b111111111111111111111000001101000 5
b11111111111111111111100000110100 4
b1111100000110100 #
b1111100000110100 &
b1111100000110100 +
b1111100000110100 1
b1111100000110100 7
b1111100000110100 %
#106000
b111111111111111111111000001101010 5
b11111111111111111111100000110101 4
b1111100000110101 #
b1111100000110101 &
b1111100000110101 +
b1111100000110101 1
b1111100000110101 7
b1111100000110101 %
#108000
b111111111111111111111000001101100 5
b11111111111111111111100000110110 4
b1111100000110110 #
b1111100000110110 &
b1111100000110110 +
b1111100000110110 1
b1111100000110110 7
b1111100000110110 %
#110000
b111111111111111111111000001101110 5
b11111111111111111111100000110111 4
b1111100000110111 #
b1111100000110111 &
b1111100000110111 +
b1111100000110111 1
b1111100000110111 7
b1111100000110111 %
#112000
b111111111111111111111000001110000 5
b11111111111111111111100000111000 4
b1111100000111000 #
b1111100000111000 &
b1111100000111000 +
b1111100000111000 1
b1111100000111000 7
b1111100000111000 %
#114000
b111111111111111111111000001110010 5
b11111111111111111111100000111001 4
b1111100000111001 #
b1111100000111001 &
b1111100000111001 +
b1111100000111001 1
b1111100000111001 7
b1111100000111001 %
#116000
b111111111111111111111000001110100 5
b11111111111111111111100000111010 4
b1111100000111010 #
b1111100000111010 &
b1111100000111010 +
b1111100000111010 1
b1111100000111010 7
b1111100000111010 %
#118000
b111111111111111111111000001110110 5
b11111111111111111111100000111011 4
b1111100000111011 #
b1111100000111011 &
b1111100000111011 +
b1111100000111011 1
b1111100000111011 7
b1111100000111011 %
#120000
b111111111111111111111000001111000 5
b11111111111111111111100000111100 4
b1111100000111100 #
b1111100000111100 &
b1111100000111100 +
b1111100000111100 1
b1111100000111100 7
b1111100000111100 %
#122000
b111111111111111111111000001111010 5
b11111111111111111111100000111101 4
b1111100000111101 #
b1111100000111101 &
b1111100000111101 +
b1111100000111101 1
b1111100000111101 7
b1111100000111101 %
#124000
b111111111111111111111000001111100 5
b11111111111111111111100000111110 4
b1111100000111110 #
b1111100000111110 &
b1111100000111110 +
b1111100000111110 1
b1111100000111110 7
b1111100000111110 %
#126000
b111111111111111111111000001111110 5
b11111111111111111111100000111111 4
b1111100000111111 #
b1111100000111111 &
b1111100000111111 +
b1111100000111111 1
b1111100000111111 7
b1111100000111111 %
#128000
b111111111111111111111000010000000 5
b11111111111111111111100001000000 4
b1111100001000000 #
b1111100001000000 &
b1111100001000000 +
b1111100001000000 1
b1111100001000000 7
b1111100001000000 %
#130000
b111111111111111111111000010000010 5
b11111111111111111111100001000001 4
b1111100001000001 #
b1111100001000001 &
b1111100001000001 +
b1111100001000001 1
b1111100001000001 7
b1111100001000001 %
#132000
b111111111111111111111000010000100 5
b11111111111111111111100001000010 4
b1111100001000010 #
b1111100001000010 &
b1111100001000010 +
b1111100001000010 1
b1111100001000010 7
b1111100001000010 %
#134000
b111111111111111111111000010000110 5
b11111111111111111111100001000011 4
b1111100001000011 #
b1111100001000011 &
b1111100001000011 +
b1111100001000011 1
b1111100001000011 7
b1111100001000011 %
#136000
b111111111111111111111000010001000 5
b11111111111111111111100001000100 4
b1111100001000100 #
b1111100001000100 &
b1111100001000100 +
b1111100001000100 1
b1111100001000100 7
b1111100001000100 %
#138000
b111111111111111111111000010001010 5
b11111111111111111111100001000101 4
b1111100001000101 #
b1111100001000101 &
b1111100001000101 +
b1111100001000101 1
b1111100001000101 7
b1111100001000101 %
#140000
b111111111111111111111000010001100 5
b11111111111111111111100001000110 4
b1111100001000110 #
b1111100001000110 &
b1111100001000110 +
b1111100001000110 1
b1111100001000110 7
b1111100001000110 %
#142000
b111111111111111111111000010001110 5
b11111111111111111111100001000111 4
b1111100001000111 #
b1111100001000111 &
b1111100001000111 +
b1111100001000111 1
b1111100001000111 7
b1111100001000111 %
#144000
b111111111111111111111000010010000 5
b11111111111111111111100001001000 4
b1111100001001000 #
b1111100001001000 &
b1111100001001000 +
b1111100001001000 1
b1111100001001000 7
b1111100001001000 %
#146000
b111111111111111111111000010010010 5
b11111111111111111111100001001001 4
b1111100001001001 #
b1111100001001001 &
b1111100001001001 +
b1111100001001001 1
b1111100001001001 7
b1111100001001001 %
#148000
b111111111111111111111000010010100 5
b11111111111111111111100001001010 4
b1111100001001010 #
b1111100001001010 &
b1111100001001010 +
b1111100001001010 1
b1111100001001010 7
b1111100001001010 %
#150000
b111111111111111111111000010010110 5
b11111111111111111111100001001011 4
b1111100001001011 #
b1111100001001011 &
b1111100001001011 +
b1111100001001011 1
b1111100001001011 7
b1111100001001011 %
#152000
b111111111111111111111000010011000 5
b11111111111111111111100001001100 4
b1111100001001100 #
b1111100001001100 &
b1111100001001100 +
b1111100001001100 1
b1111100001001100 7
b1111100001001100 %
#154000
b111111111111111111111000010011010 5
b11111111111111111111100001001101 4
b1111100001001101 #
b1111100001001101 &
b1111100001001101 +
b1111100001001101 1
b1111100001001101 7
b1111100001001101 %
#156000
b111111111111111111111000010011100 5
b11111111111111111111100001001110 4
b1111100001001110 #
b1111100001001110 &
b1111100001001110 +
b1111100001001110 1
b1111100001001110 7
b1111100001001110 %
#158000
b111111111111111111111000010011110 5
b11111111111111111111100001001111 4
b1111100001001111 #
b1111100001001111 &
b1111100001001111 +
b1111100001001111 1
b1111100001001111 7
b1111100001001111 %
#160000
b111111111111111111111000010100000 5
b11111111111111111111100001010000 4
b1111100001010000 #
b1111100001010000 &
b1111100001010000 +
b1111100001010000 1
b1111100001010000 7
b1111100001010000 %
#162000
b111111111111111111111000010100010 5
b11111111111111111111100001010001 4
b1111100001010001 #
b1111100001010001 &
b1111100001010001 +
b1111100001010001 1
b1111100001010001 7
b1111100001010001 %
#164000
b111111111111111111111000010100100 5
b11111111111111111111100001010010 4
b1111100001010010 #
b1111100001010010 &
b1111100001010010 +
b1111100001010010 1
b1111100001010010 7
b1111100001010010 %
#166000
b111111111111111111111000010100110 5
b11111111111111111111100001010011 4
b1111100001010011 #
b1111100001010011 &
b1111100001010011 +
b1111100001010011 1
b1111100001010011 7
b1111100001010011 %
#168000
b111111111111111111111000010101000 5
b11111111111111111111100001010100 4
b1111100001010100 #
b1111100001010100 &
b1111100001010100 +
b1111100001010100 1
b1111100001010100 7
b1111100001010100 %
#170000
b111111111111111111111000010101010 5
b11111111111111111111100001010101 4
b1111100001010101 #
b1111100001010101 &
b1111100001010101 +
b1111100001010101 1
b1111100001010101 7
b1111100001010101 %
#172000
b111111111111111111111000010101100 5
b11111111111111111111100001010110 4
b1111100001010110 #
b1111100001010110 &
b1111100001010110 +
b1111100001010110 1
b1111100001010110 7
b1111100001010110 %
#174000
b111111111111111111111000010101110 5
b11111111111111111111100001010111 4
b1111100001010111 #
b1111100001010111 &
b1111100001010111 +
b1111100001010111 1
b1111100001010111 7
b1111100001010111 %
#176000
b111111111111111111111000010110000 5
b11111111111111111111100001011000 4
b1111100001011000 #
b1111100001011000 &
b1111100001011000 +
b1111100001011000 1
b1111100001011000 7
b1111100001011000 %
#178000
b111111111111111111111000010110010 5
b11111111111111111111100001011001 4
b1111100001011001 #
b1111100001011001 &
b1111100001011001 +
b1111100001011001 1
b1111100001011001 7
b1111100001011001 %
#180000
b111111111111111111111000010110100 5
b11111111111111111111100001011010 4
b1111100001011010 #
b1111100001011010 &
b1111100001011010 +
b1111100001011010 1
b1111100001011010 7
b1111100001011010 %
#182000
b111111111111111111111000010110110 5
b11111111111111111111100001011011 4
b1111100001011011 #
b1111100001011011 &
b1111100001011011 +
b1111100001011011 1
b1111100001011011 7
b1111100001011011 %
#184000
b111111111111111111111000010111000 5
b11111111111111111111100001011100 4
b1111100001011100 #
b1111100001011100 &
b1111100001011100 +
b1111100001011100 1
b1111100001011100 7
b1111100001011100 %
#186000
b111111111111111111111000010111010 5
b11111111111111111111100001011101 4
b1111100001011101 #
b1111100001011101 &
b1111100001011101 +
b1111100001011101 1
b1111100001011101 7
b1111100001011101 %
#188000
b111111111111111111111000010111100 5
b11111111111111111111100001011110 4
b1111100001011110 #
b1111100001011110 &
b1111100001011110 +
b1111100001011110 1
b1111100001011110 7
b1111100001011110 %
#190000
b111111111111111111111000010111110 5
b11111111111111111111100001011111 4
b1111100001011111 #
b1111100001011111 &
b1111100001011111 +
b1111100001011111 1
b1111100001011111 7
b1111100001011111 %
#192000
b111111111111111111111000011000000 5
b11111111111111111111100001100000 4
b1111100001100000 #
b1111100001100000 &
b1111100001100000 +
b1111100001100000 1
b1111100001100000 7
b1111100001100000 %
#194000
b111111111111111111111000011000010 5
b11111111111111111111100001100001 4
b1111100001100001 #
b1111100001100001 &
b1111100001100001 +
b1111100001100001 1
b1111100001100001 7
b1111100001100001 %
#196000
b111111111111111111111000011000100 5
b11111111111111111111100001100010 4
b1111100001100010 #
b1111100001100010 &
b1111100001100010 +
b1111100001100010 1
b1111100001100010 7
b1111100001100010 %
#198000
b111111111111111111111000011000110 5
b11111111111111111111100001100011 4
b1111100001100011 #
b1111100001100011 &
b1111100001100011 +
b1111100001100011 1
b1111100001100011 7
b1111100001100011 %
#200000
b111111111111111111111000011001000 5
b11111111111111111111100001100100 4
b1111100001100100 #
b1111100001100100 &
b1111100001100100 +
b1111100001100100 1
b1111100001100100 7
b1111100001100100 %
#202000
b111111111111111111111000011001010 5
b11111111111111111111100001100101 4
b1111100001100101 #
b1111100001100101 &
b1111100001100101 +
b1111100001100101 1
b1111100001100101 7
b1111100001100101 %
#204000
b111111111111111111111000011001100 5
b11111111111111111111100001100110 4
b1111100001100110 #
b1111100001100110 &
b1111100001100110 +
b1111100001100110 1
b1111100001100110 7
b1111100001100110 %
#206000
b111111111111111111111000011001110 5
b11111111111111111111100001100111 4
b1111100001100111 #
b1111100001100111 &
b1111100001100111 +
b1111100001100111 1
b1111100001100111 7
b1111100001100111 %
#208000
b111111111111111111111000011010000 5
b11111111111111111111100001101000 4
b1111100001101000 #
b1111100001101000 &
b1111100001101000 +
b1111100001101000 1
b1111100001101000 7
b1111100001101000 %
